[
  {
    "question": "Which nodes are connected to UpdateDate where update_date is 2008-01-29, and also to another node?",
    "schema": "Graph schema: Relevant node labels and their properties (with datatypes) are:\nUpdateDate {update_date: DATE}",
    "ground_truth": "MATCH (a:UpdateDate{update_date:'2008-01-29'})-[r]->(n), (n)-[s]->(m) RETURN labels(n) AS Interim, labels(m) AS Target",
    "predicted": "MATCH (a:UpdateDate {update_date: '2008-01-29'})-[*]->(n) RETURN n.update_date, n RETURN n.update_date RETURN n.update_date RETURN n.update_date RETURN n.update_date RETURN n.update_date RETURN n.update_date RETURN n.update_date RETURN n.update_date RETURN n.update_date RETURN n.update_date RETURN n.update_date RETURN n.update_date RETURN n.update_date RETURN n.update_date RETURN n.update_date RETURN n.update_date RETURN n.update_date RETURN n.update_date RETURN n.update_date RETURN n.update_date RETURN n.update_date RETURN n.update_date RETURN n.update_date RETURN n.update_date RETURN n.update_date RETURN n.update_date RETURN n.update_date RETURN n.update_date RETURN n.update_date RETURN n.update_date RETURN n.update",
    "exact_match": 0,
    "token_f1": 0.2222222222222222,
    "structural_validity": 1
  },
  {
    "question": "Find the streams that were created before 2018 and have more than 5,000 followers.",
    "schema": "Node properties:\n- **Stream**\n  - `createdAt`: DATE_TIME Min: 2007-05-22T10:39:53.259969Z, Max: 2021-05-09T14:16:40.370294Z\n  - `id`: STRING Example: \"129004176\"\n  - `description`: STRING Example: \"Welcome to my Channel, I'm Big Chase, 31 living in\"\n  - `url`: STRING Example: \"https://www.twitch.tv/itsbigchase\"\n  - `name`: STRING Example: \"itsbigchase\"\n  - `followers`: INTEGER Min: 0, Max: 10243195\n  - `total_view_count`: INTEGER Min: 21, Max: 1451487256\n- **Game**\n  - `name`: STRING Example: \"Rust\"\n- **Language**\n  - `name`: STRING Example: \"en\"\n- **User**\n  - `name`: STRING Example: \"itsbigchase\"\n- **Team**\n  - `createdAt`: DATE_TIME Min: 2011-10-11T23:59:43.548701Z, Max: 2021-05-07T17:19:09.946382Z\n  - `name`: STRING Example: \"ESO Stream Team\"\n  - `id`: STRING Example: \"5893\"\nRelationship properties:\n\nThe relationships:\n(:Stream)-[:PLAYS]->(:Game)\n(:Stream)-[:HAS_LANGUAGE]->(:Language)\n(:Stream)-[:MODERATOR]->(:Stream)\n(:Stream)-[:MODERATOR]->(:User)\n(:Stream)-[:CHATTER]->(:Stream)\n(:Stream)-[:CHATTER]->(:User)\n(:Stream)-[:HAS_TEAM]->(:Team)\n(:Stream)-[:VIP]->(:Stream)\n(:Stream)-[:VIP]->(:User)\n(:User)-[:CHATTER]->(:Stream)\n(:User)-[:CHATTER]->(:User)\n(:User)-[:MODERATOR]->(:Stream)\n(:User)-[:MODERATOR]->(:User)",
    "ground_truth": "MATCH (s:Stream) WHERE s.createdAt < datetime('2018-01-01T00:00:00.000000Z') AND s.followers > 5000 RETURN s",
    "predicted": "->(:Stream)\n(:Stream)-[:VIP]->(:User)\n(:Stream)-[:HAS_LANGUAGE]->(:Game)\n(:Stream)-[:VIP]->(:Stream)\n(:Stream)-[:CHATTER]->(:Game)\n(:Stream)-[:VIP]->(:User)\n(:Stream)-[:HAS_TEAM]->(:Language)\n(:Stream)-[:VIP]->(:Game)\n(:Stream)-[:CHATTER]->(:Language)\n(:Stream)-[:VIP]->(:User)\n(:Stream)-[:CHATTER]->(:Language)\n(:Stream)-[:HAS_TEAM]->(:Game)\n(:Stream)-[:VIP]->(:User)\n(:Stream)-[:CHATTER]->(:Language)\n(:Stream)-[:VIP]->(:User)\n(:Stream)-[:HAS_TEAM]->(:Game)\n(:Stream)-[:VIP]->(:User)\n(:Stream)-[:CHATTER",
    "exact_match": 0,
    "token_f1": 0.0,
    "structural_validity": 0
  },
  {
    "question": "What are the top 5 tags used in questions with a score less than zero?",
    "schema": "Node properties:\n- **Question**\n  - `favorites`: INTEGER Example: \"0\"\n  - `answered`: BOOLEAN \n  - `text`: STRING Example: \"### This is:  Bug    ### Specifications  OS: Win10\"\n  - `link`: STRING Example: \"https://stackoverflow.com/questions/62224586/playg\"\n  - `createdAt`: DATE_TIME Min: 2020-06-05T16:57:19Z, Max: 2020-06-05T21:49:16Z\n  - `title`: STRING Example: \"Playground is not loading with apollo-server-lambd\"\n  - `id`: INTEGER Min: 62220505, Max: 62224586\n  - `upVotes`: INTEGER Example: \"0\"\n  - `score`: INTEGER Example: \"-1\"\n  - `downVotes`: INTEGER Example: \"1\"\n- **Tag**\n  - `name`: STRING Example: \"aws-lambda\"\n- **User**\n  - `image`: STRING Example: \"https://lh3.googleusercontent.com/-NcFYSuXU0nk/AAA\"\n  - `link`: STRING Example: \"https://stackoverflow.com/users/10251021/alexandre\"\n  - `id`: INTEGER Min: 751, Max: 13681006\n  - `reputation`: INTEGER Min: 1, Max: 420137\n  - `display_name`: STRING Example: \"Alexandre Le\"\nRelationship properties:\n\nThe relationships:\n(:Question)-[:TAGGED]->(:Tag)\n(:User)-[:ASKED]->(:Question)",
    "ground_truth": "MATCH (q:Question)-[:TAGGED]->(t:Tag) WHERE q.score < 0 RETURN t.name, count(q) AS usage ORDER BY usage DESC LIMIT 5",
    "predicted": "MATCH (u:User)-[:ASKED]->(p:Question) WHERE p.score < 0 RETURN p.id, p.name, p.upVotes, p.upDates, p.title, p.id, p.upVotes, p.upDates, p.name, p.upDates, p.upVotes, p.upDates, p.title, p.id, p.upVotes, p.upDates, p.name, p.upDates, p.title, p.id, p.upVotes, p.upDates, p.name, p.upDates, p.title, p.id, p.upVotes, p.upDates, p.name, p.upDates, p.title, p.id, p.upVotes, p.upDates, p.name, p.upDates, p.title, p.id, p.upVotes, p.upDates, p.name, p.upDates, p.title, p.id, p.upVotes, p.upD",
    "exact_match": 0,
    "token_f1": 0.3448275862068966,
    "structural_validity": 1
  },
  {
    "question": "List the labels of users with an area less than 2 and a size greater than 1.",
    "schema": "Node properties:\n- **User**\n  - `label`: STRING Example: \"inchristbl.bsky.social\"\n  - `key`: STRING Example: \"0\"\n  - `y`: FLOAT Example: \"6000.659\"\n  - `color`: STRING Example: \"#3CB371\"\n  - `x`: FLOAT Example: \"-4383.217\"\n  - `area`: FLOAT Example: \"2.6\"\n  - `size`: FLOAT Example: \"1.82\"\nRelationship properties:\n- **INTERACTED**\n  - `weight: INTEGER` Example: \"1\"\n  - `ogWeight: INTEGER` Example: \"1\"\n  - `size: FLOAT` Example: \"0.2\"\n  - `key: STRING` Example: \"geid_68_0\"\nThe relationships:\n(:User)-[:INTERACTED]->(:User)",
    "ground_truth": "MATCH (u:User) WHERE u.area < 2 AND u.size > 1 RETURN u.label",
    "predicted": "MATCH (u:User) WHERE u.area < 2 OR u.size < 1 RETURN u.key AS labels MATCH (u:User) WHERE u.area < 2 OR u.size < 1 RETURN u.key AS labels MATCH (u:User) WHERE u.area < 2 OR u.size < 1 RETURN u.key AS labels MATCH (u:User) WHERE u.area < 2 OR u.size < 1 RETURN u.key AS labels MATCH (u:User) WHERE u.area < 2 OR u.size < 1 RETURN u.key AS labels MATCH (u:User) WHERE u.area < 2 OR u.size < 1 RETURN u.key AS labels MATCH (u:User) WHERE u.area < 2 OR u.size < 1 RETURN u.key AS labels MATCH (u:User) WHERE u.area < 2 OR u.size < 1 RETURN u.key AS labels MATCH (u:User) WHERE u.area < 2 OR u.size < 1 RETURN u.key AS labels MATCH (u",
    "exact_match": 0,
    "token_f1": 0.6923076923076924,
    "structural_validity": 1
  },
  {
    "question": "Find the title and the comments for those Article where title starts with O!",
    "schema": "Graph schema: Relevant node labels and their properties (with datatypes) are:\nArticle {title: STRING}\nArticle {comments: STRING}",
    "ground_truth": "MATCH (n:Article) WHERE n.title STARTS WITH 'O' RETURN n.title AS title, n.comments AS comments",
    "predicted": "MATCH (n:Article) WHERE n.title LIKE 'O' RETURN n.title AS title, n.comments AS comments RETURN n.title AS comments RETURN n.comments AS comments RETURN n.title AS title RETURN n.title AS title RETURN n.comments AS comments RETURN n.title AS title RETURN n.title AS comments RETURN n.title AS title RETURN n.title AS title RETURN n.comments AS comments RETURN n.title AS title RETURN n.title AS comments RETURN n.comments AS comments RETURN n.title AS title RETURN n.title AS comments RETURN n.comments AS comments RETURN n.title AS title RETURN n.title AS comments RETURN n.comments AS comments RETURN n.title AS title RETURN n.title AS comments RETURN n.comments AS comments RETURN n.title AS title RETURN n.title AS comments RETURN n.comments AS comments RETURN n.title AS title RETURN n.title AS comments RETURN n.comments AS comments RETURN n.comments AS comments RETURN n.title AS title RETURN n.title AS comments RETURN n.comments AS comments RETURN n",
    "exact_match": 0,
    "token_f1": 0.8,
    "structural_validity": 1
  },
  {
    "question": "Identify streams that have moderators who are also VIPs.",
    "schema": "Node properties:\n- **Stream**\n  - `createdAt`: DATE_TIME Min: 2007-05-22T10:39:53.259969Z, Max: 2021-05-09T14:16:40.370294Z\n  - `id`: STRING Example: \"129004176\"\n  - `description`: STRING Example: \"Welcome to my Channel, I'm Big Chase, 31 living in\"\n  - `url`: STRING Example: \"https://www.twitch.tv/itsbigchase\"\n  - `name`: STRING Example: \"itsbigchase\"\n  - `followers`: INTEGER Min: 0, Max: 10243195\n  - `total_view_count`: INTEGER Min: 21, Max: 1451487256\n- **Game**\n  - `name`: STRING Example: \"Rust\"\n- **Language**\n  - `name`: STRING Example: \"en\"\n- **User**\n  - `name`: STRING Example: \"itsbigchase\"\n- **Team**\n  - `createdAt`: DATE_TIME Min: 2011-10-11T23:59:43.548701Z, Max: 2021-05-07T17:19:09.946382Z\n  - `name`: STRING Example: \"ESO Stream Team\"\n  - `id`: STRING Example: \"5893\"\nRelationship properties:\n\nThe relationships:\n(:Stream)-[:PLAYS]->(:Game)\n(:Stream)-[:HAS_LANGUAGE]->(:Language)\n(:Stream)-[:MODERATOR]->(:Stream)\n(:Stream)-[:MODERATOR]->(:User)\n(:Stream)-[:CHATTER]->(:Stream)\n(:Stream)-[:CHATTER]->(:User)\n(:Stream)-[:HAS_TEAM]->(:Team)\n(:Stream)-[:VIP]->(:Stream)\n(:Stream)-[:VIP]->(:User)\n(:User)-[:CHATTER]->(:Stream)\n(:User)-[:CHATTER]->(:User)\n(:User)-[:MODERATOR]->(:Stream)\n(:User)-[:MODERATOR]->(:User)",
    "ground_truth": "MATCH (s:Stream)<-[:MODERATOR]-(m:User)-[:VIP]->(s) RETURN s.name AS stream, m.name AS moderator_and_vip",
    "predicted": "->(:Stream)\n(:Stream)-[:VIP]->(:User)\n(:Stream)-[:HAS_LANGUAGE]->(:Game)\n(:Stream)-[:VIP]->(:Stream)\n(:Stream)-[:CHATTER]->(:Game)\n(:Stream)-[:VIP]->(:User)\n(:Stream)-[:HAS_TEAM]->(:Language)\n(:Stream)-[:VIP]->(:Game)\n(:Stream)-[:CHATTER]->(:Language)\n(:Stream)-[:VIP]->(:User)\n(:Stream)-[:CHATTER]->(:Language)\n(:Stream)-[:HAS_TEAM]->(:Game)\n(:Stream)-[:VIP]->(:User)\n(:Stream)-[:CHATTER]->(:Language)\n(:Stream)-[:VIP]->(:User)\n(:Stream)-[:HAS_TEAM]->(:Game)\n(:Stream)-[:VIP]->(:User)\n(:Stream)-[:CHATTER",
    "exact_match": 0,
    "token_f1": 0.0,
    "structural_validity": 0
  },
  {
    "question": "What are the names and ages of editors?",
    "schema": "{\"Editor\": {\"count\": 9, \"labels\": [], \"properties\": {\"Name\": {\"unique\": false, \"indexed\": false, \"type\": \"STRING\", \"existence\": false}, \"Age\": {\"unique\": false, \"indexed\": false, \"type\": \"FLOAT\", \"existence\": false}, \"Editor_ID\": {\"unique\": false, \"indexed\": false, \"type\": \"INTEGER\", \"existence\": false}}, \"type\": \"node\", \"relationships\": {\"EDited_BY\": {\"count\": 7, \"direction\": \"in\", \"labels\": [\"Journal\"], \"properties\": {\"Work_Type\": {\"indexed\": false, \"type\": \"STRING\", \"existence\": false, \"array\": false}}}}}, \"Journal\": {\"count\": 16, \"labels\": [], \"properties\": {\"Sales\": {\"unique\": false, \"indexed\": false, \"type\": \"INTEGER\", \"existence\": false}, \"Theme\": {\"unique\": false, \"indexed\": false, \"type\": \"STRING\", \"existence\": false}, \"Date\": {\"unique\": false, \"indexed\": false, \"type\": \"STRING\", \"existence\": false}, \"Journal_ID\": {\"unique\": false, \"indexed\": false, \"type\": \"INTEGER\", \"existence\": false}}, \"type\": \"node\", \"relationships\": {\"EDited_BY\": {\"count\": 0, \"direction\": \"out\", \"labels\": [\"Editor\"], \"properties\": {\"Work_Type\": {\"indexed\": false, \"type\": \"STRING\", \"existence\": false, \"array\": false}}}}}, \"EDited_BY\": {\"count\": 7, \"properties\": {\"Work_Type\": {\"indexed\": false, \"type\": \"STRING\", \"existence\": false, \"array\": false}}, \"type\": \"relationship\"}}",
    "ground_truth": "MATCH (e:Editor) RETURN e.Name, e.Age",
    "predicted": "\"Editor\": {\"count\": 9, \"labels\": [\"Journal\"], \"properties\": {\"Sales\": {\"unique\": false, \"indexed\": false, \"type\": \"INTEGER\", \"existence\": false}, \"Theme\": {\"unique\": false, \"indexed\": false, \"type\": \"STRING\", \"existence\": false}, \"Date\": {\"unique\": false, \"indexed\": false, \"type\": \"STRING\", \"existence\": false}}, \"type\": \"relationship\", \"names\": [\"Journal\"], \"ages\": {\"unique\": false, \"indexed\": false, \"type\": \"FLOAT\", \"existence\": false}\"}\n\nLes mots de résultats:\n{\"editors\": 12}\n\n### Answer:\nThe editors are editors with the following names:\n\nEditor: {\"count\": 7, \"labels\": [\"Journal\"], \"properties\": {\"Name\": {\"unique\": false, \"indexed\": false, \"type\": \"STRING\", \"existence\": false, \"array\": false}}}\n\nEditor: {\"count\": 6, \"labels\": [\"Journal\"], \"properties\": {\"Name\": {\"unique\": false, \"indexed\": false, \"",
    "exact_match": 0,
    "token_f1": 0.0,
    "structural_validity": 0
  },
  {
    "question": "Fetch the distinct values of the report_id from Report where either report_no is none provided or report_id is not null!",
    "schema": "Graph schema: Relevant node labels and their properties (with datatypes) are:\nReport {report_no: STRING}\nReport {report_id: STRING}",
    "ground_truth": "MATCH (n:Report) WHERE n.report_no = 'none provided' OR n.report_id IS NOT NULL RETURN DISTINCT n.report_id AS report_id",
    "predicted": "MATCH (n:Report) WHERE n.report_no IS NOT NULL RETURN n.report_id AS report_id ORDER BY n.report_id DESC LIMIT 1, 1 RETURN n.report_id AS report_report_id ORDER BY n.report_report_id DESC LIMIT 1, 1 RETURN n.report_report_id AS report_report_id RETURN n.report_id AS report_id ORDER BY n.report_report_id DESC LIMIT 1, 1 RETURN n.report_id AS report_id ORDER BY n.report_report_id DESC LIMIT 1, 1 RETURN n.report_id AS report_id RETURN n.report_id AS report_id RETURN n.report_id AS report_id RETURN n.report_id AS report_id RETURN n.report_id AS report_id RETURN n.report_id AS report_id RETURN n.report_id AS report_id RETURN n.report_id AS report_id RETURN n.report_id AS report_id RETURN n.report_id AS report_",
    "exact_match": 0,
    "token_f1": 0.6111111111111112,
    "structural_validity": 1
  },
  {
    "question": "Search for the article_id values from 20 Article that are linked to Journal via PUBLISHED_IN with pages = 537-560, and return article_id along with the respective Journal counts!",
    "schema": "Relevant node labels and their properties (with datatypes) are:\nArticle {article_id: INTEGER}\nJournal {}\n\nRelevant relationships are:\n{'start': Article, 'type': PUBLISHED_IN, 'end': Journal }\n\n\nRelevant relationship properties (with datatypes) are:\nPUBLISHED_IN {pages: STRING}",
    "ground_truth": "MATCH (n:Article) -[r:PUBLISHED_IN]->(m:Journal) WHERE r.pages='537-560' WITH DISTINCT n, m RETURN n.article_id AS article_id, count(m) AS count LIMIT 20",
    "predicted": "MATCH (n:Article) -[r:PUBLISHED_IN]->(m:Journal) WHERE n.article_id = r.article_id AND m.pages = 537-560 RETURN m AS article_id, count(r) AS Journal counts RETURN count(r) AS Journal counts DISTINCT count(r) AS Article_id RETURN n.article_id, count(r) AS Journal counts RETURN count(r) AS Article_id\nRETURN Article, Article_id, Journal, count(r) AS Journal, count(r) AS Article_id, count(r) AS Article_id\n\n### Result:\n(1, 20)\n\n### Explanation:\nArticle_id:\nArticle {article_id: 20, pages: 537-560, count: 1, count(r): PUBLISHED_IN}\nJournal:\nJournal {}\n\n### Keys:\n'r' - Journal counts\n- - Article_id\n\n### Dependencies:\n(Article) - PUBLISHED_IN\n(Journal) - PUBLISH",
    "exact_match": 0,
    "token_f1": 0.3076923076923077,
    "structural_validity": 1
  },
  {
    "question": "What are the total view counts for streams that have moderators?",
    "schema": "Node properties:\n- **Stream**\n  - `createdAt`: DATE_TIME Min: 2007-05-22T10:39:53.259969Z, Max: 2021-05-09T14:16:40.370294Z\n  - `id`: STRING Example: \"129004176\"\n  - `description`: STRING Example: \"Welcome to my Channel, I'm Big Chase, 31 living in\"\n  - `url`: STRING Example: \"https://www.twitch.tv/itsbigchase\"\n  - `name`: STRING Example: \"itsbigchase\"\n  - `followers`: INTEGER Min: 0, Max: 10243195\n  - `total_view_count`: INTEGER Min: 21, Max: 1451487256\n- **Game**\n  - `name`: STRING Example: \"Rust\"\n- **Language**\n  - `name`: STRING Example: \"en\"\n- **User**\n  - `name`: STRING Example: \"itsbigchase\"\n- **Team**\n  - `createdAt`: DATE_TIME Min: 2011-10-11T23:59:43.548701Z, Max: 2021-05-07T17:19:09.946382Z\n  - `name`: STRING Example: \"ESO Stream Team\"\n  - `id`: STRING Example: \"5893\"\nRelationship properties:\n\nThe relationships:\n(:Stream)-[:PLAYS]->(:Game)\n(:Stream)-[:HAS_LANGUAGE]->(:Language)\n(:Stream)-[:MODERATOR]->(:Stream)\n(:Stream)-[:MODERATOR]->(:User)\n(:Stream)-[:CHATTER]->(:Stream)\n(:Stream)-[:CHATTER]->(:User)\n(:Stream)-[:HAS_TEAM]->(:Team)\n(:Stream)-[:VIP]->(:Stream)\n(:Stream)-[:VIP]->(:User)\n(:User)-[:CHATTER]->(:Stream)\n(:User)-[:CHATTER]->(:User)\n(:User)-[:MODERATOR]->(:Stream)\n(:User)-[:MODERATOR]->(:User)",
    "ground_truth": "MATCH (s:Stream) WHERE exists{(s)-[:MODERATOR]->()} RETURN sum(s.total_view_count) AS totalViewCountForModeratedStreams",
    "predicted": "->(:Stream)\n(:Stream)-[:VIP]->(:User)\n(:Stream)-[:HAS_LANGUAGE]->(:Game)\n(:Stream)-[:VIP]->(:Stream)\n(:Stream)-[:CHATTER]->(:Game)\n(:Stream)-[:VIP]->(:User)\n(:Stream)-[:HAS_TEAM]->(:Language)\n(:Stream)-[:VIP]->(:Game)\n(:Stream)-[:CHATTER]->(:Language)\n(:Stream)-[:VIP]->(:User)\n(:Stream)-[:CHATTER]->(:Language)\n(:Stream)-[:HAS_TEAM]->(:Game)\n(:Stream)-[:VIP]->(:User)\n(:Stream)-[:CHATTER]->(:Language)\n(:Stream)-[:VIP]->(:User)\n(:Stream)-[:HAS_TEAM]->(:Game)\n(:Stream)-[:VIP]->(:User)\n(:Stream)-[:CHATTER",
    "exact_match": 0,
    "token_f1": 0.0,
    "structural_validity": 0
  },
  {
    "question": "Is there a path connecting Report where report_id is 3fa3ec8100d88908b00d139dacdedb6a and UpdateDate, for which update_date is 2014-11-11?",
    "schema": "Graph schema: Relevant node labels and their properties (with datatypes) are:\nReport {report_id: STRING}\nUpdateDate {update_date: DATE}",
    "ground_truth": "MATCH (a:Report{report_id:'3fa3ec8100d88908b00d139dacdedb6a'}), (b:UpdateDate{update_date:'2014-11-11'}) RETURN EXISTS((a)-[*]-(b)) AS pathExists",
    "predicted": "MATCH (u:Report)-[r:Report]->(m:UpdateDate) WHERE m.report_id = u.report_id RETURN FALSE;erentaining(m) ORDER BY m.update_date DESC LIMIT 1 RETURN m AS path, u ORDER BY path DESC LIMIT 1) RETURN FALSE;erentaining(m) ORDER BY path DESC LIMIT 1) RET runs(m) RETURN FALSE;erentaining(m) ORDER BY path DESC LIMIT 1) RET runs(m) RET runs(m) RET returns(m) RET runs(m) RET runs(m) RET runs(m) RET runs(m) RET runs(m) RET runs(m) RET runs(m) RET runs(m) RET runs(m) RET runs(m) RET runs(m) RET runs(m) RET runs(m) RET runs(m) RET runs(m) RET runs(m) RET runs(m) RET runs(m) RET runs(m) RET runs(m) RET runs(m) RET runs(m) RET runs(m) RET runs(m) RET runs",
    "exact_match": 0,
    "token_f1": 0.19354838709677416,
    "structural_validity": 1
  },
  {
    "question": "How many nodes are connected to Journal for which name is J. Number Theory, by exactly two different types of relationships?",
    "schema": "Graph schema: Relevant node labels and their properties (with datatypes) are:\nJournal {name: STRING}",
    "ground_truth": "MATCH (a:Journal{name:'J. Number Theory'})-[r]->(n) WITH n, COLLECT(DISTINCT TYPE(r)) AS Types WHERE SIZE(Types) = 2 RETURN COUNT(n)",
    "predicted": "MATCH (a:Journal{name:'Number Theory'})-[r]->(n) RETURN n.name, COUNT(r) AS count WHERE count > 1 RETURN count, count < 2 RETURN count RETURN count RETURN count RETURN count RETURN count RETURN count RETURN count RETURN count RETURN count RETURN count RETURN count RETURN count RETURN count RETURN count RETURN count RETURN count RETURN count RETURN count RETURN count RETURN count RETURN count RETURN count RETURN count RETURN count RETURN count RETURN count RETURN count RETURN count RETURN count RETURN count RETURN count RETURN count RETURN count RETURN count RETURN count RETURN count RETURN count RETURN count RETURN count RETURN count RETURN count RETURN count RETURN count RETURN count RETURN count RETURN count RETURN count RETURN count RETURN count RETURN count RETURN count RETURN count RETURN count RETURN count RETURN count RETURN count RETURN count RETURN count RETURN count RETURN count RETURN count RETURN count RETURN count RETURN count RETURN count RETURN count RETURN count RETURN count RETURN count RETURN count",
    "exact_match": 0,
    "token_f1": 0.39999999999999997,
    "structural_validity": 1
  },
  {
    "question": "Find the DOI for which name is 10.1016/S0393-0440(00)00003-6!",
    "schema": "Graph schema: Relevant node labels and their properties (with datatypes) are:\nDOI {name: STRING}",
    "ground_truth": "MATCH (n:DOI {name:'10.1016/S0393-0440(00)00003-6'}) RETURN n",
    "predicted": "MATCH (n:DOI{name:'10.1016/S0393-0440(00)00003-6'}) RETURN n.name RETURN n.name RETURN n.name RETURN n.name RETURN n.name RETURN n.name RETURN n.name RETURN n.name RETURN n.name RETURN n.name RETURN n.name RETURN n.name RETURN n.name RETURN n.name RETURN n.name RETURN n.name RETURN n.name RETURN n.name RETURN n.name RETURN n.name RETURN n.name RETURN n.name RETURN n.name RETURN n.name RETURN n.name RETURN n.name RETURN n.name RETURN n.name RETURN n.name RETURN n.name RETURN n.name RETURN n.name RETURN n.name RETURN n.name RETURN n.name RETURN n.name RETURN n.name RETURN n.name RETURN n.name RETURN n.name RETURN n.name RETURN n.name RETURN n.name RET",
    "exact_match": 0,
    "token_f1": 0.4000000000000001,
    "structural_validity": 1
  },
  {
    "question": "List the roles played by actors in the first 3 movies directed by Nancy Meyers.",
    "schema": "Node properties:\n- **Movie**\n  - `title`: STRING Example: \"The Matrix\"\n  - `votes`: INTEGER Min: 1, Max: 5259\n  - `tagline`: STRING Example: \"Welcome to the Real World\"\n  - `released`: INTEGER Min: 1975, Max: 2012\n- **Person**\n  - `born`: INTEGER Min: 1929, Max: 1996\n  - `name`: STRING Example: \"Keanu Reeves\"\nRelationship properties:\n- **ACTED_IN**\n  - `roles: LIST` Min Size: 1, Max Size: 6\n- **REVIEWED**\n  - `summary: STRING` Available options: ['Pretty funny at times', 'A solid romp', 'Silly, but fun', 'You had me at Jerry', 'An amazing journey', 'Slapstick redeemed only by the Robin Williams and ', 'Dark, but compelling', 'The coolest football movie ever', 'Fun, but a little far fetched']\n  - `rating: INTEGER` Min: 45, Max:  100\nThe relationships:\n(:Person)-[:ACTED_IN]->(:Movie)\n(:Person)-[:DIRECTED]->(:Movie)\n(:Person)-[:PRODUCED]->(:Movie)\n(:Person)-[:WROTE]->(:Movie)\n(:Person)-[:FOLLOWS]->(:Person)\n(:Person)-[:REVIEWED]->(:Movie)",
    "ground_truth": "MATCH (director:Person {name: \"Nancy Meyers\"})-[:DIRECTED]->(movie:Movie) WITH movie ORDER BY movie.released LIMIT 3 MATCH (actor:Person)-[actedIn:ACTED_IN]->(movie) RETURN movie.title AS MovieTitle, actor.name AS ActorName, actedIn.roles AS Roles",
    "predicted": "MATCH (p:Person)-[r:Acted_In]-(m:Acted_In)-[r:Reviewed]-(o:Reviewed)-[p:Acted_In]-(o:Reviewed) RETURN p.roles, ORDER BY p.roles DESC LIMIT 3 RETURN m.roles, ORDER BY m.roles DESC LIMIT 3 RETURN o.roles, p.roles, r.roles, m.roles, o.roles, p.roles, r.roles, m.roles, o.roles, p.roles, r.roles, m.roles, o.roles, p.roles, r.roles, m.roles, o.roles, p.roles, r.roles, m.roles, o.roles, p.roles, r.roles, m.roles, o.roles, p.roles, r.roles, m.roles, o.roles, p.roles, r.roles, m.roles, o.roles, p.roles, r.roles, m.roles, o.roles, p.roles, r.roles, m.roles, o.roles, p.roles, r.roles",
    "exact_match": 0,
    "token_f1": 0.3333333333333333,
    "structural_validity": 1
  },
  {
    "question": "Search for the journal_id in Journal that is linked through a PUBLISHED_IN relationship with Article where title is Classification of Subsystems for Local Nets with Trivial Superselection\n  Structure and PUBLISHED_IN has meta on 217!",
    "schema": "Relevant node labels and their properties (with datatypes) are:\nArticle {title: STRING}\nJournal {journal_id: STRING}\n\nRelevant relationships are:\n{'start': Article, 'type': PUBLISHED_IN, 'end': Journal }\n\n\nRelevant relationship properties (with datatypes) are:\nPUBLISHED_IN {meta: STRING}",
    "ground_truth": "MATCH (n:Article) -[pu:PUBLISHED_IN {meta : '217'}]->(m) WHERE n.title='Classification of Subsystems for Local Nets with Trivial Superselection   Structure' RETURN m.journal_id",
    "predicted": "MATCH (n:Article) -[:PUBLISHED_IN]->(m:Journal) WHERE n.title = 'Classification of Subsystems for Local Nets with Trivial Superselection' RETURN m.journal_id, n.title AS journal_id WHERE n.journal_id IS NULL RETURN n.journal_id LIMIT 1 2 3 4 5 6 7 8 9 10 11 12 13 14 15 16 17 18 19 20 21 22 23 24 25 26 27 28 29 30 RETURN m, n RETURN n, m END\n  RETURN n\n  AS journals WHERE journals.length > 10\n  ORDER BY journals ASC LIMIT 10\n  DESC LIMIT 10\n  LIMIT n\n  RETURN journals;\n\n### Result:\nJournal {journal_id: '1234567890-PUBLISHED_IN-217' }\n\n### Explanation:\nThe journals are sorted by journal_id,",
    "exact_match": 0,
    "token_f1": 0.22680412371134023,
    "structural_validity": 1
  },
  {
    "question": "Which nodes have a common property with Article where article_id is 2007 and are PUBLISHED_IN linked to a Journal?",
    "schema": "Graph schema: Relevant node labels and their properties (with datatypes) are:\nArticle {article_id: INTEGER}\nJournal {}\n\nRelevant relationships are:\n{'start': Article, 'type': PUBLISHED_IN, 'end': Journal }",
    "ground_truth": "MATCH (a:Article {article_id:'2007'})-[r:PUBLISHED_IN]->(b:Journal) WHERE ANY(key IN keys(a) WHERE a[key] = b[key]) RETURN b",
    "predicted": "MATCH (a:Article{article_id:'2007'})-[r]->(n) WITH n AS Journal RETURN n.article_id, n.type, n.article_id, n.article_id, n.article_id, n.article_id, n.article_id, n.article_id, n.article_id, n.article_id, n.article_id, n.article_id, n.article_id, n.article_id, n.article_id, n.article_id, n.article_id, n.article_id, n.article_id, n.article_id, n.article_id, n.article_id, n.article_id, n.article_id, n.article_id, n.article_id, n.article_id, n.article_id, n.article_id, n.article_id, n.article_id, n.article_id, n.article_id, n.article_id, n.article_id, n.article_id, n.article_id, n.article_id,",
    "exact_match": 0,
    "token_f1": 0.1904761904761905,
    "structural_validity": 1
  },
  {
    "question": "How many editors are there?",
    "schema": "{\"Editor\": {\"count\": 9, \"labels\": [], \"properties\": {\"Name\": {\"unique\": false, \"indexed\": false, \"type\": \"STRING\", \"existence\": false}, \"Age\": {\"unique\": false, \"indexed\": false, \"type\": \"FLOAT\", \"existence\": false}, \"Editor_ID\": {\"unique\": false, \"indexed\": false, \"type\": \"INTEGER\", \"existence\": false}}, \"type\": \"node\", \"relationships\": {\"EDited_BY\": {\"count\": 7, \"direction\": \"in\", \"labels\": [\"Journal\"], \"properties\": {\"Work_Type\": {\"indexed\": false, \"type\": \"STRING\", \"existence\": false, \"array\": false}}}}}, \"Journal\": {\"count\": 16, \"labels\": [], \"properties\": {\"Sales\": {\"unique\": false, \"indexed\": false, \"type\": \"INTEGER\", \"existence\": false}, \"Theme\": {\"unique\": false, \"indexed\": false, \"type\": \"STRING\", \"existence\": false}, \"Date\": {\"unique\": false, \"indexed\": false, \"type\": \"STRING\", \"existence\": false}, \"Journal_ID\": {\"unique\": false, \"indexed\": false, \"type\": \"INTEGER\", \"existence\": false}}, \"type\": \"node\", \"relationships\": {\"EDited_BY\": {\"count\": 0, \"direction\": \"out\", \"labels\": [\"Editor\"], \"properties\": {\"Work_Type\": {\"indexed\": false, \"type\": \"STRING\", \"existence\": false, \"array\": false}}}}}, \"EDited_BY\": {\"count\": 7, \"properties\": {\"Work_Type\": {\"indexed\": false, \"type\": \"STRING\", \"existence\": false, \"array\": false}}, \"type\": \"relationship\"}}",
    "ground_truth": "MATCH (e:Editor) RETURN COUNT(e)",
    "predicted": "MATCH (e:Editor) RETURN LIST(e) AS editors, EDITOR, EDITOR_ID, DATE, EDITOR_ID, DATE, EDITOR_ID, DATE, EDITOR_ID, DATE, EDITOR_ID, DATE, EDITOR_ID, DATE, EDITOR_ID, DATE, EDITOR_ID, DATE, EDITOR_ID, DATE, EDITOR_ID, DATE, EDITOR_ID, DATE, EDITOR_ID, DATE, EDITOR_ID, DATE, EDITOR_ID, DATE, EDITOR_ID, DATE, EDITOR_ID, DATE, EDITOR_ID, DATE, EDITOR_ID, DATE, EDITOR_ID, DATE, EDITOR_ID, DATE, EDITOR_ID, DATE, EDITOR_ID, DATE, EDITOR_ID, DATE, EDITOR_ID, DATE, EDITOR_ID, DATE, EDITOR_ID, DATE, ED",
    "exact_match": 0,
    "token_f1": 0.4285714285714285,
    "structural_validity": 1
  },
  {
    "question": "Identify characters who belong to community 579.",
    "schema": "Node properties:\n- **Character**\n  - `centrality`: FLOAT Min: 0.0, Max: 1.0\n  - `book45PageRank`: FLOAT Min: 0.15000000000000002, Max: 11.409916274911177\n  - `fastrf_embedding`: LIST Min Size: 10, Max Size: 10\n  - `book1BetweennessCentrality`: FLOAT Min: 0.0, Max: 4638.53495125504\n  - `book1PageRank`: FLOAT Min: 0.15000000000000002, Max: 8.164174336296284\n  - `louvain`: INTEGER Min: 0, Max: 10\n  - `community`: INTEGER Min: 504, Max: 795\n  - `degree`: FLOAT Min: 0.0, Max: 300.0\n  - `name`: STRING Example: \"Addam-Marbrand\"\n  - `pagerank`: FLOAT Min: 0.15000000000000002, Max: 9.473142454730429\nRelationship properties:\n- **INTERACTS**\n  - `weight: INTEGER` Min: 3, Max:  334\n- **INTERACTS1**\n  - `weight: INTEGER` Min: 3, Max:  291\n  - `book: INTEGER` Min: 1, Max:  1\n- **INTERACTS2**\n  - `weight: INTEGER` Min: 3, Max:  92\n  - `book: INTEGER` Min: 2, Max:  2\n- **INTERACTS3**\n  - `weight: INTEGER` Min: 3, Max:  95\n  - `book: INTEGER` Min: 3, Max:  3\n- **INTERACTS45**\n  - `weight: INTEGER` Min: 3, Max:  96\n  - `book: INTEGER` Min: 45, Max:  45\nThe relationships:\n(:Character)-[:INTERACTS45]->(:Character)\n(:Character)-[:INTERACTS]->(:Character)\n(:Character)-[:INTERACTS1]->(:Character)\n(:Character)-[:INTERACTS3]->(:Character)\n(:Character)-[:INTERACTS2]->(:Character)",
    "ground_truth": "MATCH (c:Character) WHERE c.community = 579 RETURN c",
    "predicted": "`weight: INTEGER` Min: 3, Max:  10,  Min: 1, Max:  15\n- **INTERACTS56**\n  - `weight: INTEGER` Min: 3, Max:  9,  Min: 0, Max:  9\n- **INTERACTS67**\n  - `weight: INTEGER` Min: 3, Max:  11,  Min: 1, Max:  14\n- **INTERACTS78**\n  - `weight: INTEGER` Min: 3, Max:  12,  Min: 1, Max:  15\n- **INTERACTS89**\n  - `weight: INTEGER` Min: 3, Max:  9,  Min: 0, Max:  9\n- **INTERACTS100**\n  - `weight: INTEGER` Min: 3, Max:  3,  Min: 1, Max:  10\n- **INTERACTS111**\n  - `weight: INTEGER` Min: 3, Max:  2,  Min: 0, Max:",
    "exact_match": 0,
    "token_f1": 0.0,
    "structural_validity": 0
  },
  {
    "question": "What is the total number of questions asked by users with a reputation greater than the average reputation of all users?",
    "schema": "Node properties:\n- **Question**\n  - `favorites`: INTEGER Example: \"0\"\n  - `answered`: BOOLEAN \n  - `text`: STRING Example: \"### This is:  Bug    ### Specifications  OS: Win10\"\n  - `link`: STRING Example: \"https://stackoverflow.com/questions/62224586/playg\"\n  - `createdAt`: DATE_TIME Min: 2020-06-05T16:57:19Z, Max: 2020-06-05T21:49:16Z\n  - `title`: STRING Example: \"Playground is not loading with apollo-server-lambd\"\n  - `id`: INTEGER Min: 62220505, Max: 62224586\n  - `upVotes`: INTEGER Example: \"0\"\n  - `score`: INTEGER Example: \"-1\"\n  - `downVotes`: INTEGER Example: \"1\"\n- **Tag**\n  - `name`: STRING Example: \"aws-lambda\"\n- **User**\n  - `image`: STRING Example: \"https://lh3.googleusercontent.com/-NcFYSuXU0nk/AAA\"\n  - `link`: STRING Example: \"https://stackoverflow.com/users/10251021/alexandre\"\n  - `id`: INTEGER Min: 751, Max: 13681006\n  - `reputation`: INTEGER Min: 1, Max: 420137\n  - `display_name`: STRING Example: \"Alexandre Le\"\nRelationship properties:\n\nThe relationships:\n(:Question)-[:TAGGED]->(:Tag)\n(:User)-[:ASKED]->(:Question)",
    "ground_truth": "MATCH (u:User) WITH avg(u.reputation) AS averageReputation MATCH (u:User)-[:ASKED]->(q:Question) WHERE u.reputation > averageReputation RETURN count(DISTINCT q) AS questionCount",
    "predicted": "MATCH (u:User)-[:ASKED]->(q:Question) WHERE q.reputation > N/A RETURN QUAD(N-1, CASE WHEN q.id = '62224586' OR q.id = '751')) AS ncount\n\n### Key:\n KEY: DATE_FORMAT_DISTINCT\n\n### Patient:\n RESULTED WITH: 10251021\n\n### Key: INTEGER\n\n### Response:\n  [\n  [\n    [\n      [\n        [\n          [\n            [\n              [\n                [\n                  [\n                    [\n                      :Question\n                  '1. How do I know that the average reputation of all users is 1.1?', true ): true,\n                  [\n                    [\n                      '2. The reputation of all users is distributed over a wide range of sizes, with the largest being 64,500, and the smallest being 1,000. '\n                  ]\n                  ]\n                  ]\n                  ]\n                  ]\n                  ]\n                  ]\n                  ]\n                  ]\n                 \n  ]\n  ]\n  ]\n  ]\n  [\n  ]\n  ]\n  [\n  ]\n  ]\n  [",
    "exact_match": 0,
    "token_f1": 0.15584415584415587,
    "structural_validity": 1
  },
  {
    "question": "Is there a path connecting Author where first_name is Bernhard and Topic, for which description is Focusing on techniques and concepts related to transformations, solutions, and properties of linear equations and matrices, including Jordan normal form, eigenvalues, eigenvectors, diagonalization, and eigenformulations.?",
    "schema": "Graph schema: Relevant node labels and their properties (with datatypes) are:\nAuthor {first_name: STRING}\nTopic {description: STRING}",
    "ground_truth": "MATCH (a:Author{first_name:'Bernhard'}), (b:Topic{description:'Focusing on techniques and concepts related to transformations, solutions, and properties of linear equations and matrices, including Jordan normal form, eigenvalues, eigenvectors, diagonalization, and eigenformulations.'}) RETURN EXISTS((a)-[*]-(b)) AS pathExists",
    "predicted": "MATCH (n:Author{first_name:'Bernhard'})-[r:Topic]->(m) WHERE n.description ='Focusing on techniques and concepts related to transformations, solutions, and properties of linear equations and matrices, including Jordan normal form, eigenvalues, eigenvectors, diagonalization, and eigenformulations' RETURN m) RETURN n.description RETURN n.first_name RETURN m RETURN r RETURN m RETURN m RETURN n.description RETURN n.description RETURN n.first_name RETURN n.first_name RETURN n.description RETURN n.description RETURN n.description RETURN n.first_name RETURN n.first_name RETURN n.description RETURN n.description RETURN n.description RETURN n.first_name RETURN n.first_name RETURN n.description RETURN n.description RETURN n.description RETURN n.description RETURN n.description RETURN n.description RETURN n.description RETURN n.first_name RETURN n.first_name RETURN n.description RETURN n.description RETURN n.description RETURN n.description RETURN n.description RETURN n.",
    "exact_match": 0,
    "token_f1": 0.7333333333333334,
    "structural_validity": 1
  },
  {
    "question": "List the types of relationships and their counts connected to Article for which comments is Published by Geometry and Topology at\n  http://www.maths.warwick.ac.uk/gt/GTVol4/paper14.abs.html!",
    "schema": "Graph schema: Relevant node labels and their properties (with datatypes) are:\nArticle {comments: STRING}",
    "ground_truth": "MATCH (a:Article{comments:'Published by Geometry and Topology at   http://www.maths.warwick.ac.uk/gt/GTVol4/paper14.abs.html'})-[r]->() RETURN TYPE(r) AS Relations, COUNT(r) AS Counts",
    "predicted": "MATCH (a:Article{comments:'Published by Geometry and Topology at...'})-[r]->(n) RETURN types(r) AS types, count(r) AS count, count(n) AS count, count(r) AS count, count(n) AS count, count(r) AS count, count(n) AS count, count(r) AS count, count(n) AS count, count(r) AS count, count(n) AS count, count(r) AS count, count(n) AS count, count(r) AS count, count(n) AS count, count(r) AS count, count(n) AS count, count(r) AS count, count(n) AS count, count(r) AS count, count(n) AS count, count(r) AS count, count(n) AS count, count(r) AS count, count(n) AS count, count(r) AS count, count(n) AS count, count(r) AS count, count(n) AS count, count(r) AS count, count(n) AS count, count(r) AS count, count(n)",
    "exact_match": 0,
    "token_f1": 0.5714285714285714,
    "structural_validity": 1
  },
  {
    "question": "How many gymnasts are there?",
    "schema": "{\"Gymnast\": {\"count\": 7, \"labels\": [], \"properties\": {\"Pommel_Horse_Points\": {\"unique\": false, \"indexed\": false, \"type\": \"FLOAT\", \"existence\": false}, \"Rings_Points\": {\"unique\": false, \"indexed\": false, \"type\": \"FLOAT\", \"existence\": false}, \"Floor_Exercise_Points\": {\"unique\": false, \"indexed\": false, \"type\": \"FLOAT\", \"existence\": false}, \"Gymnast_ID\": {\"unique\": false, \"indexed\": false, \"type\": \"INTEGER\", \"existence\": false}, \"Vault_Points\": {\"unique\": false, \"indexed\": false, \"type\": \"FLOAT\", \"existence\": false}, \"Total_Points\": {\"unique\": false, \"indexed\": false, \"type\": \"FLOAT\", \"existence\": false}, \"Parallel_Bars_Points\": {\"unique\": false, \"indexed\": false, \"type\": \"FLOAT\", \"existence\": false}, \"Horizontal_Bar_Points\": {\"unique\": false, \"indexed\": false, \"type\": \"FLOAT\", \"existence\": false}}, \"type\": \"node\", \"relationships\": {}}, \"Person\": {\"count\": 10, \"labels\": [], \"properties\": {\"Name\": {\"unique\": false, \"indexed\": false, \"type\": \"STRING\", \"existence\": false}, \"Age\": {\"unique\": false, \"indexed\": false, \"type\": \"FLOAT\", \"existence\": false}, \"Height\": {\"unique\": false, \"indexed\": false, \"type\": \"FLOAT\", \"existence\": false}, \"Hometown\": {\"unique\": false, \"indexed\": false, \"type\": \"STRING\", \"existence\": false}, \"People_ID\": {\"unique\": false, \"indexed\": false, \"type\": \"INTEGER\", \"existence\": false}}, \"type\": \"node\", \"relationships\": {}}}",
    "ground_truth": "MATCH (n:Gymnast) RETURN count(n)",
    "predicted": "\"Gymnast\": {\"count\": 10, \"labels\": [\"Person\", \"Person\", \"Person\", \"Person\", \"Person\", \"Person\", \"Person\", \"Person\", \"Person\", \"Person\", \"Person\", \"Person\", \"Person\", \"Person\", \"Person\", \"Person\", \"Person\", \"Person\", \"Person\", \"Person\", \"Person\", \"Person\", \"Person\", \"Person\", \"Person\", \"Person\", \"Person\", \"Person\", \"Person\", \"Person\", \"Person\", \"Person\", \"Person\", \"Person\", \"Person\", \"Person\", \"Person\", \"Person\", \"Person\", \"Person\", \"Person\", \"Person\", \"Person\", \"Person\", \"Person\", \"Person\", \"Person\", \"Person\", \"Person\", \"Person\", \"Person\", \"Person\", \"Person\", \"Person\", \"Person\", \"Person\", \"Person\", \"Person\", \"Person\", \"Person\", \"Person\", \"Person\", \"Person\", \"Person\", \"Person\", \"Person\", \"Person\", \"Person\", \"Person\", \"Person\", \"Person\", \"Person\", \"Person\", \"Person\", \"Person\", \"Person\", \"Person\", \"Person\", \"Person\", \"Person\",",
    "exact_match": 0,
    "token_f1": 0.0,
    "structural_validity": 0
  },
  {
    "question": "Find the question with the least number of upvotes and a score greater than the average score of questions tagged with 'aws-lambda'.",
    "schema": "Node properties:\n- **Question**\n  - `favorites`: INTEGER Example: \"0\"\n  - `answered`: BOOLEAN \n  - `text`: STRING Example: \"### This is:  Bug    ### Specifications  OS: Win10\"\n  - `link`: STRING Example: \"https://stackoverflow.com/questions/62224586/playg\"\n  - `createdAt`: DATE_TIME Min: 2020-06-05T16:57:19Z, Max: 2020-06-05T21:49:16Z\n  - `title`: STRING Example: \"Playground is not loading with apollo-server-lambd\"\n  - `id`: INTEGER Min: 62220505, Max: 62224586\n  - `upVotes`: INTEGER Example: \"0\"\n  - `score`: INTEGER Example: \"-1\"\n  - `downVotes`: INTEGER Example: \"1\"\n- **Tag**\n  - `name`: STRING Example: \"aws-lambda\"\n- **User**\n  - `image`: STRING Example: \"https://lh3.googleusercontent.com/-NcFYSuXU0nk/AAA\"\n  - `link`: STRING Example: \"https://stackoverflow.com/users/10251021/alexandre\"\n  - `id`: INTEGER Min: 751, Max: 13681006\n  - `reputation`: INTEGER Min: 1, Max: 420137\n  - `display_name`: STRING Example: \"Alexandre Le\"\nRelationship properties:\n\nThe relationships:\n(:Question)-[:TAGGED]->(:Tag)\n(:User)-[:ASKED]->(:Question)",
    "ground_truth": "MATCH (t:Tag {name: 'aws-lambda'})<-[:TAGGED]-(q:Question) WITH avg(q.score) AS average_score MATCH (q:Question) WHERE q.score > average_score WITH q ORDER BY q.upVotes ASC RETURN q LIMIT 1",
    "predicted": "MATCH (q:Question) WHERE q.name <> 'playg' RETURN q.id, q.upVotes, q.score, q.downVotes, q.name, q.upVotes, q.upVotes, q.score, q.downVotes, q.name, q.downVotes, q.id, q.upVotes, q.upVotes, q.score, q.downVotes, q.name, q.downVotes, q.id, q.upVotes, q.upVotes, q.score, q.downVotes, q.name, q.downVotes, q.id, q.upVotes, q.upVotes, q.score, q.downVotes, q.name, q.downVotes, q.id, q.upVotes, q.upVotes, q.score, q.downVotes, q.name, q.downVotes, q.id, q.upVotes, q.upVotes, q.score, q.downVotes, q.name, q.downVotes, q",
    "exact_match": 0,
    "token_f1": 0.30303030303030304,
    "structural_validity": 1
  },
  {
    "question": "Are there any nodes that are connected with Report where report_no is none provided and share a common property with DOI, for which name equals 10.1016/S0040-9383(00)00015-X?",
    "schema": "Graph schema: Relevant node labels and their properties (with datatypes) are:\nReport {report_no: STRING}\nDOI {name: STRING}",
    "ground_truth": "MATCH (a:Report{report_no:'none provided'})-[r]->(n), (d:DOI{name:'10.1016/S0040-9383(00)00015-X'}) WHERE ANY(key in keys(n) WHERE n[key] = d[key]) RETURN n",
    "predicted": "MATCH (a:Report{report_no:'0'})-[*]->(n) RETURN properties(n) AS properties_copied, properties_copied, properties_copied, properties_copied, properties_copied, properties_copied, properties_copied, properties_copied, properties_copied, properties_copied, properties_copied, properties_copied, properties_copied, properties_copied, properties_copied, properties_copied, properties_copied, properties_copied, properties_copied, properties_copied, properties_copied, properties_copied, properties_copied, properties_copied, properties_copied, properties_copied, properties_copied, properties_copied, properties_copied, properties_copied, properties_copied, properties_copied, properties_copied, properties_copied, properties_copied, properties_copied, properties_copied, properties_copied, properties_copied, properties_copied, properties_copied, properties_copied, properties_copied, properties_copied, properties_copied, properties_cop",
    "exact_match": 0,
    "token_f1": 0.2,
    "structural_validity": 1
  },
  {
    "question": "List the movies that have been both directed and produced by the same person.",
    "schema": "Node properties:\n- **Movie**\n  - `title`: STRING Example: \"The Matrix\"\n  - `votes`: INTEGER Min: 1, Max: 5259\n  - `tagline`: STRING Example: \"Welcome to the Real World\"\n  - `released`: INTEGER Min: 1975, Max: 2012\n- **Person**\n  - `born`: INTEGER Min: 1929, Max: 1996\n  - `name`: STRING Example: \"Keanu Reeves\"\nRelationship properties:\n- **ACTED_IN**\n  - `roles: LIST` Min Size: 1, Max Size: 6\n- **REVIEWED**\n  - `summary: STRING` Available options: ['Pretty funny at times', 'A solid romp', 'Silly, but fun', 'You had me at Jerry', 'An amazing journey', 'Slapstick redeemed only by the Robin Williams and ', 'Dark, but compelling', 'The coolest football movie ever', 'Fun, but a little far fetched']\n  - `rating: INTEGER` Min: 45, Max:  100\nThe relationships:\n(:Person)-[:ACTED_IN]->(:Movie)\n(:Person)-[:DIRECTED]->(:Movie)\n(:Person)-[:PRODUCED]->(:Movie)\n(:Person)-[:WROTE]->(:Movie)\n(:Person)-[:FOLLOWS]->(:Person)\n(:Person)-[:REVIEWED]->(:Movie)",
    "ground_truth": "MATCH (p:Person)-[:DIRECTED]->(m:Movie)<-[:PRODUCED]-(p) RETURN m.title AS movie",
    "predicted": "MATCH (p:Person)-[:DIRECTED]->(m:Movie) RETURN p.title, m.title, m.released, m.year, p.year, p.year, m.year, p.year, p.year, m.year, p.year, m.year, p.year, m.year, p.year, m.year, p.year, m.year, p.year, m.year, p.year, m.year, p.year, m.year, p.year, m.year, p.year, m.year, p.year, m.year, p.year, m.year, p.year, m.year, p.year, m.year, p.year, m.year, p.year, m.year, p.year, m.year, p.year, m.year, p.year, m.year, p.year, m.year, p.year, m.year, p.year, m.year, p.year, m.year, p.year, m.year, p.year, m.year, p.year",
    "exact_match": 0,
    "token_f1": 0.26666666666666666,
    "structural_validity": 1
  },
  {
    "question": "Which streams are moderated by users who are also VIPs in the same stream?",
    "schema": "Node properties:\n- **Stream**\n  - `createdAt`: DATE_TIME Min: 2007-05-22T10:39:53.259969Z, Max: 2021-05-09T14:16:40.370294Z\n  - `id`: STRING Example: \"129004176\"\n  - `description`: STRING Example: \"Welcome to my Channel, I'm Big Chase, 31 living in\"\n  - `url`: STRING Example: \"https://www.twitch.tv/itsbigchase\"\n  - `name`: STRING Example: \"itsbigchase\"\n  - `followers`: INTEGER Min: 0, Max: 10243195\n  - `total_view_count`: INTEGER Min: 21, Max: 1451487256\n- **Game**\n  - `name`: STRING Example: \"Rust\"\n- **Language**\n  - `name`: STRING Example: \"en\"\n- **User**\n  - `name`: STRING Example: \"itsbigchase\"\n- **Team**\n  - `createdAt`: DATE_TIME Min: 2011-10-11T23:59:43.548701Z, Max: 2021-05-07T17:19:09.946382Z\n  - `name`: STRING Example: \"ESO Stream Team\"\n  - `id`: STRING Example: \"5893\"\nRelationship properties:\n\nThe relationships:\n(:Stream)-[:PLAYS]->(:Game)\n(:Stream)-[:HAS_LANGUAGE]->(:Language)\n(:Stream)-[:MODERATOR]->(:Stream)\n(:Stream)-[:MODERATOR]->(:User)\n(:Stream)-[:CHATTER]->(:Stream)\n(:Stream)-[:CHATTER]->(:User)\n(:Stream)-[:HAS_TEAM]->(:Team)\n(:Stream)-[:VIP]->(:Stream)\n(:Stream)-[:VIP]->(:User)\n(:User)-[:CHATTER]->(:Stream)\n(:User)-[:CHATTER]->(:User)\n(:User)-[:MODERATOR]->(:Stream)\n(:User)-[:MODERATOR]->(:User)",
    "ground_truth": "MATCH (s:Stream)<-[:MODERATOR]-(u:User)-[:VIP]->(s) RETURN s.name AS stream_name, u.name AS moderator_vip_name",
    "predicted": "->(:Stream)\n(:Stream)-[:VIP]->(:User)\n(:Stream)-[:HAS_LANGUAGE]->(:Game)\n(:Stream)-[:VIP]->(:Stream)\n(:Stream)-[:CHATTER]->(:Game)\n(:Stream)-[:VIP]->(:User)\n(:Stream)-[:HAS_TEAM]->(:Language)\n(:Stream)-[:VIP]->(:Game)\n(:Stream)-[:CHATTER]->(:Language)\n(:Stream)-[:VIP]->(:User)\n(:Stream)-[:CHATTER]->(:Language)\n(:Stream)-[:HAS_TEAM]->(:Game)\n(:Stream)-[:VIP]->(:User)\n(:Stream)-[:CHATTER]->(:Language)\n(:Stream)-[:VIP]->(:User)\n(:Stream)-[:HAS_TEAM]->(:Game)\n(:Stream)-[:VIP]->(:User)\n(:Stream)-[:CHATTER",
    "exact_match": 0,
    "token_f1": 0.0,
    "structural_validity": 0
  },
  {
    "question": "Find abstract of the Article and return it along with the count of Journal that are linked via PUBLISHED_IN where year is 2002!",
    "schema": "Relevant node labels and their properties (with datatypes) are:\nArticle {abstract: STRING}\nJournal {}\n\nRelevant relationships are:\n{'start': Article, 'type': PUBLISHED_IN, 'end': Journal }\n\n\nRelevant relationship properties (with datatypes) are:\nPUBLISHED_IN {year: STRING}",
    "ground_truth": "MATCH (n:Article) -[r:PUBLISHED_IN]->(m:Journal) WHERE r.year = '2002' RETURN n.abstract AS abstract, count(m) AS count",
    "predicted": "MATCH (n:Article) -[*]->(m:Journal)-[*]->(t) WHERE n.year = '2002' RETURN t, m.abstract, n.count(t) AS count RETURN count DISTINCT count(m) RETURN n.abstract RETURN n.abstract RETURN count(m) RETURN count(t) RETURN count(m) RETURN n.abstract RETURN n.abstract RETURN count(m) RETURN count(t) RETURN count(m) RETURN n.abstract RETURN n.abstract RETURN count(m) RETURN count(t) RETURN count(m) RETURN count(t) RETURN count(m) RETURN count(n) RETURN count(m) DISTINCT count(n) RETURN count(m) DISTINCT count(t) RETURN count(m) DISTINCT count(n) RETURN count(m) DISTINCT count(t) RETURN count(m) DISTINCT count(n) RETURN count(m) DISTINCT count(n)\n\n\n### Cypher:",
    "exact_match": 0,
    "token_f1": 0.6060606060606061,
    "structural_validity": 1
  },
  {
    "question": "What are the first 3 languages spoken in streams with more than 10,000 followers?",
    "schema": "Node properties:\n- **Stream**\n  - `createdAt`: DATE_TIME Min: 2007-05-22T10:39:53.259969Z, Max: 2021-05-09T14:16:40.370294Z\n  - `id`: STRING Example: \"129004176\"\n  - `description`: STRING Example: \"Welcome to my Channel, I'm Big Chase, 31 living in\"\n  - `url`: STRING Example: \"https://www.twitch.tv/itsbigchase\"\n  - `name`: STRING Example: \"itsbigchase\"\n  - `followers`: INTEGER Min: 0, Max: 10243195\n  - `total_view_count`: INTEGER Min: 21, Max: 1451487256\n- **Game**\n  - `name`: STRING Example: \"Rust\"\n- **Language**\n  - `name`: STRING Example: \"en\"\n- **User**\n  - `name`: STRING Example: \"itsbigchase\"\n- **Team**\n  - `createdAt`: DATE_TIME Min: 2011-10-11T23:59:43.548701Z, Max: 2021-05-07T17:19:09.946382Z\n  - `name`: STRING Example: \"ESO Stream Team\"\n  - `id`: STRING Example: \"5893\"\nRelationship properties:\n\nThe relationships:\n(:Stream)-[:PLAYS]->(:Game)\n(:Stream)-[:HAS_LANGUAGE]->(:Language)\n(:Stream)-[:MODERATOR]->(:Stream)\n(:Stream)-[:MODERATOR]->(:User)\n(:Stream)-[:CHATTER]->(:Stream)\n(:Stream)-[:CHATTER]->(:User)\n(:Stream)-[:HAS_TEAM]->(:Team)\n(:Stream)-[:VIP]->(:Stream)\n(:Stream)-[:VIP]->(:User)\n(:User)-[:CHATTER]->(:Stream)\n(:User)-[:CHATTER]->(:User)\n(:User)-[:MODERATOR]->(:Stream)\n(:User)-[:MODERATOR]->(:User)",
    "ground_truth": "MATCH (s:Stream)-[:HAS_LANGUAGE]->(l:Language) WHERE s.followers > 10000 RETURN l.name AS language, count(*) AS count ORDER BY count DESC LIMIT 3",
    "predicted": "->(:Stream)\n(:Stream)-[:VIP]->(:User)\n(:Stream)-[:HAS_LANGUAGE]->(:Game)\n(:Stream)-[:VIP]->(:Stream)\n(:Stream)-[:CHATTER]->(:Game)\n(:Stream)-[:VIP]->(:User)\n(:Stream)-[:HAS_TEAM]->(:Language)\n(:Stream)-[:VIP]->(:Game)\n(:Stream)-[:CHATTER]->(:Language)\n(:Stream)-[:VIP]->(:User)\n(:Stream)-[:CHATTER]->(:Language)\n(:Stream)-[:HAS_TEAM]->(:Game)\n(:Stream)-[:VIP]->(:User)\n(:Stream)-[:CHATTER]->(:Language)\n(:Stream)-[:VIP]->(:User)\n(:Stream)-[:HAS_TEAM]->(:Game)\n(:Stream)-[:VIP]->(:User)\n(:Stream)-[:CHATTER",
    "exact_match": 0,
    "token_f1": 0.0,
    "structural_validity": 0
  },
  {
    "question": "Which nodes are at the end of a path starting from Article, with title equal to  Summation and transformation formulas for elliptic hypergeometric series, passing through DOI via HAS_DOI?",
    "schema": "Graph schema: Relevant node labels and their properties (with datatypes) are:\nArticle {title: STRING}\nDOI {}\n\nRelevant relationships are:\n{'start': Article, 'type': HAS_DOI, 'end': DOI }",
    "ground_truth": "MATCH (a:Article{title:'Summation and transformation formulas for elliptic hypergeometric series'})-[:HAS_DOI]->(c:DOI)-[r]->(n) RETURN n",
    "predicted": "MATCH (a:Article{title:'Summation and transformation formulas for elliptic hypergeometric series'})-[*]->(d:DOI) WHERE d.title = 'Summation and transformation formulas for elliptic hypergeometric series' RETURN d.end, d.title RETURN d.end RETURN d.end RETURN d.end RETURN d.end RETURN d.end RETURN d.end RETURN d.end RETURN d.end RETURN d.end RETURN d.end RETURN d.end RETURN d.end RETURN d.end RETURN d.end RETURN d.end RETURN d.end RETURN d.end RETURN d.end RETURN d.end RETURN d.end RETURN d.end RETURN d.end RETURN d.end RETURN d.end RETURN d.end RETURN d.end RETURN d.end RETURN d.end RETURN d.end RETURN d.end RETURN d.end RETURN d.end RETURN d.end RETURN d.end RETURN d.end RETURN d.end RETURN d.end RETURN d.end RETURN d",
    "exact_match": 0,
    "token_f1": 0.6206896551724137,
    "structural_validity": 1
  },
  {
    "question": "Retrieve the category_id for Categories that is linked through a HAS_CATEGORY relationship with the Article where article_id is 603207!",
    "schema": "Graph schema: Relevant node labels and their properties (with datatypes) are:\nArticle {article_id: INTEGER}\nCategories {category_id: STRING}\n\nRelevant relationships are:\n{'start': Article, 'type': HAS_CATEGORY, 'end': Categories }",
    "ground_truth": "MATCH (n:Article) -[ha:HAS_CATEGORY]->(m) WHERE n.article_id='603207' RETURN m.category_id",
    "predicted": "MATCH (n:Article) WHERE n.article_id IS NULL RETURN n.category_id AS category_id RETURN n.category_id AS category_id RETURN n.category_id AS category_id RETURN n.category_id AS category_id RETURN n.category_id AS category_id RETURN n.category_id AS category_id RETURN n.category_id AS category_id RETURN n.category_id AS category_id RETURN n.category_id AS category_id RETURN n.category_id AS category_id RETURN n.category_id AS category_id RETURN n.category_id AS category_id RETURN n.category_id AS category_id RETURN n.category_id AS category_id RETURN n.category_id AS category_id RETURN n.category_id AS category_id RETURN n.category_id AS category_id RETURN n.category_id AS category_id RETURN n.category_id AS category_id RETURN n.category_id AS category_id RETURN n.category_id AS category_id RETURN n.category_id AS category_",
    "exact_match": 0,
    "token_f1": 0.4444444444444444,
    "structural_validity": 1
  },
  {
    "question": "Which nodes are connected to Author where first_name is A., and also to another node?",
    "schema": "Graph schema: Relevant node labels and their properties (with datatypes) are:\nAuthor {first_name: STRING}",
    "ground_truth": "MATCH (a:Author{first_name:'A.'})-[r]->(n), (n)-[s]->(m) RETURN labels(n) AS Interim, labels(m) AS Target",
    "predicted": "MATCH (a:Author{first_name:'A'})-[r]->(n) RETURN nodes(n) AS Author, nodes(r) AS Other WHERE nodes(r) IS NOT NULL RETURN nodes(n) AS Author, nodes(r) IS NOT NULL RETURN nodes(r) IS NOT NULL RETURN nodes(n) AS Other WHERE nodes(n) IS NOT NULL Limit 2!\n\n### Result:\n(1, 'Author')) RETURN Authors(nodes(n)) AS Author, (2, 'Other')) RETURN Other\n(2, 'Author'))\n\n### Explanation:\nThe Author nodes are connected to Author by their first_name. The Other nodes are also connected to Author by their first_name.\n\n### Keypoints:\nAuthor: Relationship to Other\n\n### Only:\n(3, 'Other'))\n\n### Keypoints:\nAuthor: Relationship to Author\n\n### Keys:\nd1:Author\n\n### Keys:\nn1:Other\n\n### Fills:\nAuthor: Relationship to Author\n\n### Keys:\nr1:Node {first_name:'A'}\n\n### Keys:\np1:",
    "exact_match": 0,
    "token_f1": 0.11320754716981131,
    "structural_validity": 1
  },
  {
    "question": "Which streams have the most distinct games played? List the top 5.",
    "schema": "Node properties:\n- **Stream**\n  - `createdAt`: DATE_TIME Min: 2007-05-22T10:39:53.259969Z, Max: 2021-05-09T14:16:40.370294Z\n  - `id`: STRING Example: \"129004176\"\n  - `description`: STRING Example: \"Welcome to my Channel, I'm Big Chase, 31 living in\"\n  - `url`: STRING Example: \"https://www.twitch.tv/itsbigchase\"\n  - `name`: STRING Example: \"itsbigchase\"\n  - `followers`: INTEGER Min: 0, Max: 10243195\n  - `total_view_count`: INTEGER Min: 21, Max: 1451487256\n- **Game**\n  - `name`: STRING Example: \"Rust\"\n- **Language**\n  - `name`: STRING Example: \"en\"\n- **User**\n  - `name`: STRING Example: \"itsbigchase\"\n- **Team**\n  - `createdAt`: DATE_TIME Min: 2011-10-11T23:59:43.548701Z, Max: 2021-05-07T17:19:09.946382Z\n  - `name`: STRING Example: \"ESO Stream Team\"\n  - `id`: STRING Example: \"5893\"\nRelationship properties:\n\nThe relationships:\n(:Stream)-[:PLAYS]->(:Game)\n(:Stream)-[:HAS_LANGUAGE]->(:Language)\n(:Stream)-[:MODERATOR]->(:Stream)\n(:Stream)-[:MODERATOR]->(:User)\n(:Stream)-[:CHATTER]->(:Stream)\n(:Stream)-[:CHATTER]->(:User)\n(:Stream)-[:HAS_TEAM]->(:Team)\n(:Stream)-[:VIP]->(:Stream)\n(:Stream)-[:VIP]->(:User)\n(:User)-[:CHATTER]->(:Stream)\n(:User)-[:CHATTER]->(:User)\n(:User)-[:MODERATOR]->(:Stream)\n(:User)-[:MODERATOR]->(:User)",
    "ground_truth": "MATCH (s:Stream)-[:PLAYS]->(g:Game) WITH s, COUNT(DISTINCT g) AS distinctGames ORDER BY distinctGames DESC LIMIT 5 RETURN s.name AS streamName, distinctGames",
    "predicted": "->(:Stream)\n(:Stream)-[:VIP]->(:User)\n(:Stream)-[:HAS_LANGUAGE]->(:Game)\n(:Stream)-[:VIP]->(:Stream)\n(:Stream)-[:CHATTER]->(:Game)\n(:Stream)-[:VIP]->(:User)\n(:Stream)-[:HAS_TEAM]->(:Language)\n(:Stream)-[:VIP]->(:Game)\n(:Stream)-[:CHATTER]->(:Language)\n(:Stream)-[:VIP]->(:User)\n(:Stream)-[:CHATTER]->(:Language)\n(:Stream)-[:HAS_TEAM]->(:Game)\n(:Stream)-[:VIP]->(:User)\n(:Stream)-[:CHATTER]->(:Language)\n(:Stream)-[:VIP]->(:User)\n(:Stream)-[:HAS_TEAM]->(:Game)\n(:Stream)-[:VIP]->(:User)\n(:Stream)-[:CHATTER",
    "exact_match": 0,
    "token_f1": 0.0,
    "structural_validity": 0
  },
  {
    "question": "List the top 5 movies with a tagline containing 'football'.",
    "schema": "Node properties:\n- **Movie**\n  - `title`: STRING Example: \"The Matrix\"\n  - `votes`: INTEGER Min: 1, Max: 5259\n  - `tagline`: STRING Example: \"Welcome to the Real World\"\n  - `released`: INTEGER Min: 1975, Max: 2012\n- **Person**\n  - `born`: INTEGER Min: 1929, Max: 1996\n  - `name`: STRING Example: \"Keanu Reeves\"\nRelationship properties:\n- **ACTED_IN**\n  - `roles: LIST` Min Size: 1, Max Size: 6\n- **REVIEWED**\n  - `summary: STRING` Available options: ['Pretty funny at times', 'A solid romp', 'Silly, but fun', 'You had me at Jerry', 'An amazing journey', 'Slapstick redeemed only by the Robin Williams and ', 'Dark, but compelling', 'The coolest football movie ever', 'Fun, but a little far fetched']\n  - `rating: INTEGER` Min: 45, Max:  100\nThe relationships:\n(:Person)-[:ACTED_IN]->(:Movie)\n(:Person)-[:DIRECTED]->(:Movie)\n(:Person)-[:PRODUCED]->(:Movie)\n(:Person)-[:WROTE]->(:Movie)\n(:Person)-[:FOLLOWS]->(:Person)\n(:Person)-[:REVIEWED]->(:Movie)",
    "ground_truth": "MATCH (m:Movie) WHERE m.tagline CONTAINS 'football' RETURN m ORDER BY m.released DESC LIMIT 5",
    "predicted": "MATCH (p:Person)-[r:ACTED_IN]-(m:Movie)-[d:DIRECTED]-(o:Reviewed)-[n:Reviewed]-(p:Person)-[r:DIRECTED]-(m:Movie)-[c:Reviewed]-(o:Reviewed)-[w:Reviewed]-(p:Person)-[r:DIRECTED]-(m:Movie)-[d:Directed]-(o:Reviewed)-[n:Reviewed]-(p:Person)-[r:ACTED_IN]->(:Movie) RETURN p.name AS m_name, r.title AS r_title, d.year AS d_year, c.year AS c_year, w.year AS w_year, p.year As p_year, n.year As n_year, p.title As p_title, m.year As m_year, o.year As o_year, p.year As p_year, d.year As d_year, c.year As c_year, w.year As w_year, p.year As p_year, m.year As m_",
    "exact_match": 0,
    "token_f1": 0.1,
    "structural_validity": 1
  },
  {
    "question": "Which streams have a follower count between 1000 and 5000 and play the game 'Rust'?",
    "schema": "Node properties:\n- **Stream**\n  - `createdAt`: DATE_TIME Min: 2007-05-22T10:39:53.259969Z, Max: 2021-05-09T14:16:40.370294Z\n  - `id`: STRING Example: \"129004176\"\n  - `description`: STRING Example: \"Welcome to my Channel, I'm Big Chase, 31 living in\"\n  - `url`: STRING Example: \"https://www.twitch.tv/itsbigchase\"\n  - `name`: STRING Example: \"itsbigchase\"\n  - `followers`: INTEGER Min: 0, Max: 10243195\n  - `total_view_count`: INTEGER Min: 21, Max: 1451487256\n- **Game**\n  - `name`: STRING Example: \"Rust\"\n- **Language**\n  - `name`: STRING Example: \"en\"\n- **User**\n  - `name`: STRING Example: \"itsbigchase\"\n- **Team**\n  - `createdAt`: DATE_TIME Min: 2011-10-11T23:59:43.548701Z, Max: 2021-05-07T17:19:09.946382Z\n  - `name`: STRING Example: \"ESO Stream Team\"\n  - `id`: STRING Example: \"5893\"\nRelationship properties:\n\nThe relationships:\n(:Stream)-[:PLAYS]->(:Game)\n(:Stream)-[:HAS_LANGUAGE]->(:Language)\n(:Stream)-[:MODERATOR]->(:Stream)\n(:Stream)-[:MODERATOR]->(:User)\n(:Stream)-[:CHATTER]->(:Stream)\n(:Stream)-[:CHATTER]->(:User)\n(:Stream)-[:HAS_TEAM]->(:Team)\n(:Stream)-[:VIP]->(:Stream)\n(:Stream)-[:VIP]->(:User)\n(:User)-[:CHATTER]->(:Stream)\n(:User)-[:CHATTER]->(:User)\n(:User)-[:MODERATOR]->(:Stream)\n(:User)-[:MODERATOR]->(:User)",
    "ground_truth": "MATCH (s:Stream)-[:PLAYS]->(:Game {name: 'Rust'}) WHERE s.followers >= 1000 AND s.followers <= 5000 RETURN s.name AS stream, s.followers AS followerCount",
    "predicted": "->(:Stream)\n(:Stream)-[:VIP]->(:User)\n(:Stream)-[:HAS_LANGUAGE]->(:Game)\n(:Stream)-[:VIP]->(:Stream)\n(:Stream)-[:CHATTER]->(:Game)\n(:Stream)-[:VIP]->(:User)\n(:Stream)-[:HAS_TEAM]->(:Language)\n(:Stream)-[:VIP]->(:Game)\n(:Stream)-[:CHATTER]->(:Language)\n(:Stream)-[:VIP]->(:User)\n(:Stream)-[:CHATTER]->(:Language)\n(:Stream)-[:HAS_TEAM]->(:Game)\n(:Stream)-[:VIP]->(:User)\n(:Stream)-[:CHATTER]->(:Language)\n(:Stream)-[:VIP]->(:User)\n(:Stream)-[:HAS_TEAM]->(:Game)\n(:Stream)-[:VIP]->(:User)\n(:Stream)-[:CHATTER",
    "exact_match": 0,
    "token_f1": 0.0,
    "structural_validity": 0
  },
  {
    "question": "Find the Article for which comments is 21 pages, AMS-LaTeX!",
    "schema": "Graph schema: Relevant node labels and their properties (with datatypes) are:\nArticle {comments: STRING}",
    "ground_truth": "MATCH (n:Article {comments:'21 pages, AMS-LaTeX'}) RETURN n",
    "predicted": "MATCH (n:Article) WHERE n.comments IS NOT NULL RETURN n AS Article WHERE n.comments IS NOT NULL RETURN n.Article AS Report RETURN Report AS Summary RETURN Report AS Comments RETURN n.Comment AS Name RETURN n.Name AS Title RETURN n.Name AS Title RETURN n.Name AS Title RETURN n.Comment AS Name RETURN n.Name AS Title RETURN n.Comment AS Title RETURN n.Article AS Name RETURN n.Article AS Report RETURN n.Article AS Report RETURN n.Reports AS Report RETURN Report AS Report RETURN Report AS Summary RETURN Report AS Summary RETURN Report AS Summary RETURN Report AS Summary RETURN Report AS Summary RETURN Report AS Summary RETURN Report AS Summary RETURN Report AS Summary RETURN Report AS Summary RETURN Report AS Summary RETURN Report AS Summary RETURN Report AS Summary RETURN Report AS Summary RETURN Report AS Summary RETURN Report AS Summary RETURN Report AS Summary RETURN Report AS Summary RETURN Report AS Summary RETURN Report AS Summary RETURN Report AS Summary RETURN Report AS Summary RETURN Report AS Summary RETURN Report AS Summary RETURN Report AS Summary RETURN Report AS Summary RETURN Report AS Summary",
    "exact_match": 0,
    "token_f1": 0.2222222222222222,
    "structural_validity": 1
  },
  {
    "question": "Search for the name in Journal that is linked through a PUBLISHED_IN relationship with Article where article_id is 6147 and PUBLISHED_IN has meta on 227!",
    "schema": "Relevant node labels and their properties (with datatypes) are:\nArticle {article_id: INTEGER}\nJournal {name: STRING}\n\nRelevant relationships are:\n{'start': Article, 'type': PUBLISHED_IN, 'end': Journal }\n\n\nRelevant relationship properties (with datatypes) are:\nPUBLISHED_IN {meta: STRING}",
    "ground_truth": "MATCH (n:Article) -[pu:PUBLISHED_IN {meta : '227'}]->(m) WHERE n.article_id='6147' RETURN m.name",
    "predicted": "MATCH (n:Article) -[r:PUBLISHED_IN]->(m:Journal) WHERE n.name = '6147' RETURN m.name AS name WHERE n.name IS NOT NULL RETURN n.name AS name RETURN n.name AS name RETURN n.name AS name RETURN n.name AS name RETURN n.name AS name RETURN m.name AS name RETURN m.name AS name RETURN m.name AS name RETURN r.name AS name RETURN r.name AS name RETURN r.name AS name RETURN m.name AS name RETURN m.name AS name RETURN n.name AS name RETURN n.name AS name RETURN n.name AS name RETURN n.name AS name RETURN n.name AS name RETURN m.name AS name RETURN m.name AS name RETURN m.name AS name RETURN r.name AS name RETURN r.name AS name RETURN m.name AS name RETURN m.name AS name RETURN n.name AS name RETURN n.name AS name RETURN n.name AS name RETURN m.name AS name RETURN m.",
    "exact_match": 0,
    "token_f1": 0.38461538461538464,
    "structural_validity": 1
  },
  {
    "question": "How many nodes are connected to Topic for which cluster is 9, by exactly two different types of relationships?",
    "schema": "Graph schema: Relevant node labels and their properties (with datatypes) are:\nTopic {cluster: INTEGER}",
    "ground_truth": "MATCH (a:Topic{cluster:'9'})-[r]->(n) WITH n, COLLECT(DISTINCT TYPE(r)) AS Types WHERE SIZE(Types) = 2 RETURN COUNT(n)",
    "predicted": "MATCH (a:Topic{cluster:'9'})-[*]->(d) WHERE d.type='relationship' RETURN count(a) AS count_nodes RETURN count(d) AS count_repeats RETURN count(a) AS count_repeats RETURN count(d) AS count_repeats RETURN count(a) AS count_repeats RETURN count(d) AS count_repeats DISTANCE count_nodes count_repeats RETURN count(a) AS count_nodes RETURN count(d) AS count_repeats RETURN count(a) AS count_repeats RETURN count(d) AS count_repeats DISTANCE count_nodes count_repeats RETURN count(a) AS count_repeats RETURN count(d) AS count_repeats DISTANCE count(a) AS count_repeats RETURN count(d) AS count_repeats DISTANCE count(a) AS count_repeats RETURN count(d) AS count_repeats DISTANCE count(a) AS count_repeats RETURN count(d",
    "exact_match": 0,
    "token_f1": 0.30769230769230765,
    "structural_validity": 1
  },
  {
    "question": "Enumerate the properties of nodes that are either directly or indirectly connected to Author for which last_name is Mason!",
    "schema": "Graph schema: Relevant node labels and their properties (with datatypes) are:\nAuthor {last_name: STRING}",
    "ground_truth": "MATCH (a:Author{last_name:'Mason'})-[*]->(n) RETURN DISTINCT properties(n) AS Properties",
    "predicted": "MATCH (a:Author{last_name:'Mason'})-[r]->(n) RETURN properties(n) AS properties_directly_connected, properties_indirectly_connected, properties_not_directly_connected, properties_indirectly_connected, properties_not_indirectly_connected, properties_not_indirectly_connected, properties_not_indirectly_connected, properties_not_indirectly_connected, properties_not_indirectly_connected) WHERE properties_directly_connected = true AND properties_indirectly_connected = true AND properties_not_directly_connected = true AND properties_indirectly_connected = true AND properties_not_directly_connected = true AND properties_indirectly_connected = true AND properties_not_indirectly_connected = true AND properties_not_indirectly_connected = true AND properties_not_indirectly_connected = true AND properties_not_indirectly_connected = true AND properties_not_indirectly_connected = true AND properties_not_indirectly_connected = true AND properties_not_indirectly_connected = true",
    "exact_match": 0,
    "token_f1": 0.32,
    "structural_validity": 1
  },
  {
    "question": "Are there any nodes that are connected with Article where title is Free Field Construction for the ABF Models in Regime II and share a common property with UpdateDate, for which update_date equals 2008-01-29?",
    "schema": "Graph schema: Relevant node labels and their properties (with datatypes) are:\nArticle {title: STRING}\nUpdateDate {update_date: DATE}",
    "ground_truth": "MATCH (a:Article{title:'Free Field Construction for the ABF Models in Regime II'})-[r]->(n), (d:UpdateDate{update_date:'2008-01-29'}) WHERE ANY(key in keys(n) WHERE n[key] = d[key]) RETURN n",
    "predicted": "MATCH (a:Article{title:'Free Field Construction for the ABF Models in Regime II'})-[*]->(n) RETURN properties(n) AS properties_updated_date, properties_updated_date, properties_updated_date, properties_updated_date, properties_updated_date, properties_updated_date, properties_updated_date, properties_updated_date, properties_updated_date, properties_updated_date, properties_updated_date, properties_updated_date, properties_updated_date, properties_updated_date, properties_updated_date, properties_updated_date, properties_updated_date, properties_updated_date, properties_updated_date, properties_updated_date, properties_updated_date, properties_updated_date, properties_updated_date, properties_updated_date, properties_updated_date, properties_updated_date, properties_updated_date, properties_updated_date, properties_updated_date, properties_updated_date, properties_updated_date, properties_updated_date, properties_updated_date, properties_updated_date, properties_updated_date, properties_updated_date, properties_updated",
    "exact_match": 0,
    "token_f1": 0.6111111111111112,
    "structural_validity": 1
  },
  {
    "question": "Find comments of the Article and return it along with the count of Journal that are linked via PUBLISHED_IN where pages is 641-672!",
    "schema": "Relevant node labels and their properties (with datatypes) are:\nArticle {comments: STRING}\nJournal {}\n\nRelevant relationships are:\n{'start': Article, 'type': PUBLISHED_IN, 'end': Journal }\n\n\nRelevant relationship properties (with datatypes) are:\nPUBLISHED_IN {pages: STRING}",
    "ground_truth": "MATCH (n:Article) -[r:PUBLISHED_IN]->(m:Journal) WHERE r.pages = '641-672' RETURN n.comments AS comments, count(m) AS count",
    "predicted": "MATCH (n:Article) -[r:PUBLISHED_IN]->(m:Journal) WHERE n.pages = 641-672 RETURN m AS comments, count(r:PUBLISHED_IN) RETURN count(r:PUBLISHED_IN) RETURN comments; Catch any errors and return them.\n\n\n### Key-Mapping:\nAssociate node labels with their properties (with datatypes) and relationships with those.\nArticle {comments: STRING}\nJournal {}\n\n### Key-Direction:\nDirection: FOLLOW\n\n### Key-Expression:\nx(Article {comments: STRING}) {count(r:PUBLISHED_IN) <- count(r:PUBLISHED_IN)}\n\n\n### Key-Direction:\nFOLLOW\n\n### Result:\nReturns:\nArticle {comments: STRING}\nJournal {}\n\n### Key-Expression:\nx(Article {comments: STRING}) {count(r:PUBLISHED_IN) <- count(r:PUBLISHED_IN)}\n\n\n### Key-Direction:\nFOL",
    "exact_match": 0,
    "token_f1": 0.26229508196721313,
    "structural_validity": 1
  },
  {
    "question": "List the types of relationships and their counts connected to Article for which article_id is 1071!",
    "schema": "Graph schema: Relevant node labels and their properties (with datatypes) are:\nArticle {article_id: INTEGER}",
    "ground_truth": "MATCH (a:Article{article_id:'1071'})-[r]->() RETURN TYPE(r) AS Relations, COUNT(r) AS Counts",
    "predicted": "MATCH (a:Article{article_id:'1071'})-[r]->(n) RETURN types(r) AS types, count(r) AS counts RETURN counts AS counts, type(n) AS types, count(r) AS counts RETURN counts AS counts, type(r) AS types, count(r) AS counts RETURN counts AS counts, type(n) AS types, count(r) AS types, count(r) AS counts RETURN counts RETURN counts, type(n) AS types, count(r) AS types, count(r) AS types, count(r) AS types, count(n) AS types, count(r) AS types, count(n) AS types, count(r) AS types, count(n) AS types, count(r) AS types, count(n) AS types, count(r) AS types, count(n) AS types, count(r) AS types, count(n) AS types, count(r) AS types, count(n) AS types, count(r) AS types, count(n) AS types, count(r) AS types, count(n) AS types",
    "exact_match": 0,
    "token_f1": 0.2857142857142857,
    "structural_validity": 1
  },
  {
    "question": "List the distinct properties of nodes that are 2 hops away from Report with report_no equal to PAM-780!",
    "schema": "Graph schema: Relevant node labels and their properties (with datatypes) are:\nReport {report_no: STRING}",
    "ground_truth": "MATCH (a:Report{report_no:'PAM-780'})-[*2]->(n) RETURN DISTINCT properties(n) AS props",
    "predicted": "MATCH (a:Report{report_no:'PAM-780'})-[*]->(n) RETURN DISTINCT properties(n) AS properties_2_hats WHERE properties_2_hats != 'DO NOT MATCH ANY NAMES' RETURN properties_2_hats AS properties_2_hats RETURN properties_2_hats AS properties_2_hats RETURN properties_2_hats AS properties_2_hats RETURN properties_2_hats AS properties_2_hats RETURN properties_2_hats AS properties_2_hats RETURN properties_2_hats AS properties_2_hats RETURN properties_2_hats AS properties_2_hats RETURN properties_2_hats AS properties_2_hats RETURN properties_2_hats AS properties_2_hats RETURN properties_2_hats AS properties_2_hats RETURN properties_2_hats AS properties_2_hats RETURN properties_2_hats AS properties_2_hats RETURN properties_2_hats AS properties_2_hats",
    "exact_match": 0,
    "token_f1": 0.5,
    "structural_validity": 1
  },
  {
    "question": "Which 3 users have VIP status on the most streams?",
    "schema": "Node properties:\n- **Stream**\n  - `createdAt`: DATE_TIME Min: 2007-05-22T10:39:53.259969Z, Max: 2021-05-09T14:16:40.370294Z\n  - `id`: STRING Example: \"129004176\"\n  - `description`: STRING Example: \"Welcome to my Channel, I'm Big Chase, 31 living in\"\n  - `url`: STRING Example: \"https://www.twitch.tv/itsbigchase\"\n  - `name`: STRING Example: \"itsbigchase\"\n  - `followers`: INTEGER Min: 0, Max: 10243195\n  - `total_view_count`: INTEGER Min: 21, Max: 1451487256\n- **Game**\n  - `name`: STRING Example: \"Rust\"\n- **Language**\n  - `name`: STRING Example: \"en\"\n- **User**\n  - `name`: STRING Example: \"itsbigchase\"\n- **Team**\n  - `createdAt`: DATE_TIME Min: 2011-10-11T23:59:43.548701Z, Max: 2021-05-07T17:19:09.946382Z\n  - `name`: STRING Example: \"ESO Stream Team\"\n  - `id`: STRING Example: \"5893\"\nRelationship properties:\n\nThe relationships:\n(:Stream)-[:PLAYS]->(:Game)\n(:Stream)-[:HAS_LANGUAGE]->(:Language)\n(:Stream)-[:MODERATOR]->(:Stream)\n(:Stream)-[:MODERATOR]->(:User)\n(:Stream)-[:CHATTER]->(:Stream)\n(:Stream)-[:CHATTER]->(:User)\n(:Stream)-[:HAS_TEAM]->(:Team)\n(:Stream)-[:VIP]->(:Stream)\n(:Stream)-[:VIP]->(:User)\n(:User)-[:CHATTER]->(:Stream)\n(:User)-[:CHATTER]->(:User)\n(:User)-[:MODERATOR]->(:Stream)\n(:User)-[:MODERATOR]->(:User)",
    "ground_truth": "MATCH (u:User)-[:VIP]->(s:Stream) WITH u, COUNT(s) AS vip_stream_count ORDER BY vip_stream_count DESC LIMIT 3 RETURN u.name AS userName, vip_stream_count",
    "predicted": "->(:Stream)\n(:Stream)-[:VIP]->(:User)\n(:Stream)-[:HAS_LANGUAGE]->(:Game)\n(:Stream)-[:VIP]->(:Stream)\n(:Stream)-[:CHATTER]->(:Game)\n(:Stream)-[:VIP]->(:User)\n(:Stream)-[:HAS_TEAM]->(:Language)\n(:Stream)-[:VIP]->(:Game)\n(:Stream)-[:CHATTER]->(:Language)\n(:Stream)-[:VIP]->(:User)\n(:Stream)-[:CHATTER]->(:Language)\n(:Stream)-[:HAS_TEAM]->(:Game)\n(:Stream)-[:VIP]->(:User)\n(:Stream)-[:CHATTER]->(:Language)\n(:Stream)-[:VIP]->(:User)\n(:Stream)-[:HAS_TEAM]->(:Game)\n(:Stream)-[:VIP]->(:User)\n(:Stream)-[:CHATTER",
    "exact_match": 0,
    "token_f1": 0.0,
    "structural_validity": 0
  },
  {
    "question": "What are the descriptions of streams that play 'Call of Duty: Warzone'?",
    "schema": "Node properties:\n- **Stream**\n  - `createdAt`: DATE_TIME Min: 2007-05-22T10:39:53.259969Z, Max: 2021-05-09T14:16:40.370294Z\n  - `id`: STRING Example: \"129004176\"\n  - `description`: STRING Example: \"Welcome to my Channel, I'm Big Chase, 31 living in\"\n  - `url`: STRING Example: \"https://www.twitch.tv/itsbigchase\"\n  - `name`: STRING Example: \"itsbigchase\"\n  - `followers`: INTEGER Min: 0, Max: 10243195\n  - `total_view_count`: INTEGER Min: 21, Max: 1451487256\n- **Game**\n  - `name`: STRING Example: \"Rust\"\n- **Language**\n  - `name`: STRING Example: \"en\"\n- **User**\n  - `name`: STRING Example: \"itsbigchase\"\n- **Team**\n  - `createdAt`: DATE_TIME Min: 2011-10-11T23:59:43.548701Z, Max: 2021-05-07T17:19:09.946382Z\n  - `name`: STRING Example: \"ESO Stream Team\"\n  - `id`: STRING Example: \"5893\"\nRelationship properties:\n\nThe relationships:\n(:Stream)-[:PLAYS]->(:Game)\n(:Stream)-[:HAS_LANGUAGE]->(:Language)\n(:Stream)-[:MODERATOR]->(:Stream)\n(:Stream)-[:MODERATOR]->(:User)\n(:Stream)-[:CHATTER]->(:Stream)\n(:Stream)-[:CHATTER]->(:User)\n(:Stream)-[:HAS_TEAM]->(:Team)\n(:Stream)-[:VIP]->(:Stream)\n(:Stream)-[:VIP]->(:User)\n(:User)-[:CHATTER]->(:Stream)\n(:User)-[:CHATTER]->(:User)\n(:User)-[:MODERATOR]->(:Stream)\n(:User)-[:MODERATOR]->(:User)",
    "ground_truth": "MATCH (s:Stream)-[:PLAYS]->(g:Game {name: 'Call of Duty: Warzone'}) RETURN s.description AS StreamDescription",
    "predicted": "->(:Stream)\n(:Stream)-[:VIP]->(:User)\n(:Stream)-[:HAS_LANGUAGE]->(:Game)\n(:Stream)-[:VIP]->(:Stream)\n(:Stream)-[:CHATTER]->(:Game)\n(:Stream)-[:VIP]->(:User)\n(:Stream)-[:HAS_TEAM]->(:Language)\n(:Stream)-[:VIP]->(:Game)\n(:Stream)-[:CHATTER]->(:Language)\n(:Stream)-[:VIP]->(:User)\n(:Stream)-[:CHATTER]->(:Language)\n(:Stream)-[:HAS_TEAM]->(:Game)\n(:Stream)-[:VIP]->(:User)\n(:Stream)-[:CHATTER]->(:Language)\n(:Stream)-[:VIP]->(:User)\n(:Stream)-[:HAS_TEAM]->(:Game)\n(:Stream)-[:VIP]->(:User)\n(:Stream)-[:CHATTER",
    "exact_match": 0,
    "token_f1": 0.0,
    "structural_validity": 0
  },
  {
    "question": "How many unique relationships originate from Article where abstract is   The Wakimoto construction for the quantum affine algebra U_q(\\hat{sl}_2)\nadmits a reduction to the q-deformed parafermion algebras. We interpret the\nlatter theory as a free field realization of the Andrews-Baxter-Forrester\nmodels in regime II. We give multi-particle form factors of some local\noperators on the lattice and compute their scaling limit, where the models are\ndescribed by a massive field theory with Z_k symmetric minimal scattering\nmatrices.\n?",
    "schema": "Graph schema: Relevant node labels and their properties (with datatypes) are:\nArticle {abstract: STRING}",
    "ground_truth": "MATCH (a:Article{abstract:'  The Wakimoto construction for the quantum affine algebra U_q(\\hat{sl}_2) admits a reduction to the q-deformed parafermion algebras. We interpret the latter theory as a free field realization of the Andrews-Baxter-Forrester models in regime II. We give multi-particle form factors of some local operators on the lattice and compute their scaling limit, where the models are described by a massive field theory with Z_k symmetric minimal scattering matrices. '})-[r]->() RETURN COUNT(DISTINCT TYPE(r)) AS rels, TYPE(r)",
    "predicted": "MATCH (n:Article) WHERE n.abstract LIKE 'The Wakimoto construction for the quantum affine algebra U_q(\\hat{sl}_2)' RETURN count(n.properties) AS relationships, count(n.properties) AS count_relationships RETURN count(n) AS unique_relationships RETURN count(n) AS unique_relationships RETURN count(n) AS count_relationships RETURN count(n) AS unique_relationships RETURN count(n) AS unique_relationships RETURN count(n) AS count_relationships RETURN count(n) AS unique_relationships RETURN count(n) AS unique_relationships RETURN count(n) AS count_relationships RETURN count(n) AS unique_relationships RETURN count(n) AS unique_relationships RETURN count(n) AS unique_relationships RETURN count(n) AS unique_relationships RETURN count(n) AS unique_relationships RETURN count(n) AS unique_relationships RETURN count(n) AS unique_relationships RETURN count(n) AS unique_relationships RETURN count(n) AS unique_relationships RETURN count(n) AS unique_relationships RETURN count(n) AS unique_relationships RET",
    "exact_match": 0,
    "token_f1": 0.2325581395348837,
    "structural_validity": 1
  },
  {
    "question": "List characters with the lowest 5 book1PageRanks.",
    "schema": "Node properties:\n- **Character**\n  - `centrality`: FLOAT Min: 0.0, Max: 1.0\n  - `book45PageRank`: FLOAT Min: 0.15000000000000002, Max: 11.409916274911177\n  - `fastrf_embedding`: LIST Min Size: 10, Max Size: 10\n  - `book1BetweennessCentrality`: FLOAT Min: 0.0, Max: 4638.53495125504\n  - `book1PageRank`: FLOAT Min: 0.15000000000000002, Max: 8.164174336296284\n  - `louvain`: INTEGER Min: 0, Max: 10\n  - `community`: INTEGER Min: 504, Max: 795\n  - `degree`: FLOAT Min: 0.0, Max: 300.0\n  - `name`: STRING Example: \"Addam-Marbrand\"\n  - `pagerank`: FLOAT Min: 0.15000000000000002, Max: 9.473142454730429\nRelationship properties:\n- **INTERACTS**\n  - `weight: INTEGER` Min: 3, Max:  334\n- **INTERACTS1**\n  - `weight: INTEGER` Min: 3, Max:  291\n  - `book: INTEGER` Min: 1, Max:  1\n- **INTERACTS2**\n  - `weight: INTEGER` Min: 3, Max:  92\n  - `book: INTEGER` Min: 2, Max:  2\n- **INTERACTS3**\n  - `weight: INTEGER` Min: 3, Max:  95\n  - `book: INTEGER` Min: 3, Max:  3\n- **INTERACTS45**\n  - `weight: INTEGER` Min: 3, Max:  96\n  - `book: INTEGER` Min: 45, Max:  45\nThe relationships:\n(:Character)-[:INTERACTS45]->(:Character)\n(:Character)-[:INTERACTS]->(:Character)\n(:Character)-[:INTERACTS1]->(:Character)\n(:Character)-[:INTERACTS3]->(:Character)\n(:Character)-[:INTERACTS2]->(:Character)",
    "ground_truth": "MATCH (c:Character) WHERE c.book1PageRank IS NOT NULL RETURN c.name AS character, c.book1PageRank AS pageRank ORDER BY pageRank LIMIT 5",
    "predicted": "`weight: INTEGER` Min: 3, Max:  10,  Min: 1, Max:  15\n- **INTERACTS56**\n  - `weight: INTEGER` Min: 3, Max:  9,  Min: 0, Max:  9\n- **INTERACTS67**\n  - `weight: INTEGER` Min: 3, Max:  11,  Min: 1, Max:  14\n- **INTERACTS78**\n  - `weight: INTEGER` Min: 3, Max:  12,  Min: 1, Max:  15\n- **INTERACTS89**\n  - `weight: INTEGER` Min: 3, Max:  9,  Min: 0, Max:  9\n- **INTERACTS100**\n  - `weight: INTEGER` Min: 3, Max:  3,  Min: 1, Max:  10\n- **INTERACTS111**\n  - `weight: INTEGER` Min: 3, Max:  2,  Min: 0, Max:",
    "exact_match": 0,
    "token_f1": 0.0,
    "structural_validity": 0
  },
  {
    "question": "Look for the comments of the Article that is not related  to the Report with the  report_id  5049b80a2935f95cc95cf14dbfb8c610!",
    "schema": "Graph schema: Relevant node labels and their properties (with datatypes) are:\nArticle {comments: STRING}\nReport {report_id: STRING}",
    "ground_truth": "MATCH (n:Article), (:Report {report_id: '5049b80a2935f95cc95cf14dbfb8c610'}) WHERE NOT (n) --> (:Report) RETURN n.comments",
    "predicted": "MATCH (n:Article) WHERE NOT n.comments LIKE '5049b80a2935f95cc95cf14dbfb8c610' RETURN n.report_id, n.comments ORDER BY n.report_id DESC LIMIT 1  MINutestrings(::comments) RETURN n.report_id, n.comments DESC LIMIT 1  MATCH (m:Report) WHERE NOT m.comments LIKE '5049b80a2935f95cc95cf14dbfb8c610' RETURN m.comments ORDER BY m.comments DESC LIMIT 1  MATCH (m:Report) WHERE NOT m.comments LIKE '5049b80a2935f95cc95cf14dbfb8c610' RETURN m.comments ORDER BY m.comments DESC LIMIT 1  MATCH (m:Report) WHERE NOT m.comments LIKE '5049b80a2935f95cc95cf14dbfb",
    "exact_match": 0,
    "token_f1": 0.3225806451612903,
    "structural_validity": 1
  },
  {
    "question": "For each Article, find the number of Author linked via WRITTEN_BY and retrieve the abstract of the Article and the Author counts in ascending order!",
    "schema": "Graph schema: Relevant node labels and their properties (with datatypes) are:\nArticle {abstract: STRING}\nAuthor {}\n\nRelevant relationships are:\n{'start': Article, 'type': WRITTEN_BY, 'end': Author }",
    "ground_truth": "MATCH (n:Article) -[:WRITTEN_BY]->(m:Author) WITH DISTINCT n, m RETURN n.abstract AS abstract, count(m) AS author_count ORDER BY author_count",
    "predicted": "MATCH (n:Article) -[r:Author]->(m:Author) WHERE n.abstract = 'Example' RETURN n.abstract, COUNT(m.abstract) AS counts, count(n) RETURN counts, counts ASC, counts DESC, counts ASC, counts DESC, counts ASC, counts DESC, counts ASC, counts DESC, counts ASC, counts DESC, counts ASC, counts DESC, counts ASC, counts DESC, counts ASC, counts DESC, counts ASC, counts DESC, counts ASC, counts DESC, counts ASC, counts DESC, counts ASC, counts DESC, counts ASC, counts DESC, counts ASC, counts DESC, counts ASC, counts DESC, counts ASC, counts DESC, counts ASC, counts DESC, counts ASC, counts DESC, counts ASC, counts DESC, counts ASC, counts DESC, counts ASC, counts DESC, counts ASC, counts DESC, counts ASC, counts DESC, counts ASC, counts DESC, counts ASC, counts DESC, counts ASC, counts DESC, counts ASC, counts DESC, counts ASC, counts DESC, counts ASC, counts DESC, counts ASC",
    "exact_match": 0,
    "token_f1": 0.3125,
    "structural_validity": 1
  },
  {
    "question": "List the properties of nodes that are 3 hops away from Article with article_id equal to 1063!",
    "schema": "Graph schema: Relevant node labels and their properties (with datatypes) are:\nArticle {article_id: INTEGER}",
    "ground_truth": "MATCH (a:Article)-[*3]->(n) WHERE a.article_id = '1063' RETURN properties(n) AS props",
    "predicted": "MATCH (a:Article{article_id:'1063'})-[*3]->(n) RETURN properties(n) AS properties_3 WHERE properties_3 <> n RETURN properties(n) AS properties_2 RETURN properties_2 AS properties_1 RETURN properties(n) AS properties_1 RETURN properties(n) AS properties_0 RETURN properties(n) AS properties_0 RETURN properties(n) AS properties_0 RETURN properties(n) AS properties_1 RETURN properties(n) AS properties_1 RETURN properties(n) AS properties_2 RETURN properties(n) AS properties_2 RETURN properties(n) AS properties_3 RETURN properties(n) AS properties_3 RETURN properties(n) AS properties_4 RETURN properties(n) AS properties_4 RETURN properties(n) AS properties_5 RETURN properties(n) AS properties_5 RETURN properties(n) AS properties_6 RETURN properties(n) AS properties_6 RETURN properties(n) AS properties_7 RETURN properties(n) AS properties_7 RETURN properties(n) AS properties_8 RETURN properties(n",
    "exact_match": 0,
    "token_f1": 0.35714285714285715,
    "structural_validity": 1
  },
  {
    "question": "How many paths are there between Author where last_name is Leoni and Topic, for which cluster equals 6?",
    "schema": "Graph schema: Relevant node labels and their properties (with datatypes) are:\nAuthor {last_name: STRING}\nTopic {cluster: INTEGER}",
    "ground_truth": "MATCH p=(a:Author{last_name:'Leoni'})-[*]->(d:Topic{cluster:'6'}) RETURN count(p)",
    "predicted": "MATCH (a:Author{last_name:'Leoni'})-[r]->(n) RETURN count(r) AS paths, count(n) AS counts, count(r) AS counts, count(n) AS counts, count(r) AS counts, count(n) AS counts, count(r) AS counts, count(n) AS counts, count(n) AS counts, count(r) AS counts, count(n) AS counts, count(r) AS counts, count(n) AS counts, count(r) AS counts, count(n) AS counts, count(r) AS counts, count(n) AS counts, count(r) AS counts, count(n) AS counts, count(r) AS counts, count(n) AS counts, count(r) AS counts, count(n) AS counts, count(r) AS counts, count(n) AS counts, count(r) AS counts, count(n) AS counts, count(r) AS counts, count(n) AS counts, count(r) AS counts, count(n) AS counts, count(r) AS counts, count(n) AS counts, count",
    "exact_match": 0,
    "token_f1": 0.30769230769230765,
    "structural_validity": 1
  }
]